LEVEL - 2 Arithmetic Verilog HDL Problems/4. Fixed Point Restoring Divider/1. Synchronous FIFO/synchronous_fifo_8bit.v
module synchronous_fifo_8bit(data_out,full,empty,data_in,wr_en,re_en,clk,reset);

    output reg [7:0] data_out;
    output wire full,empty;
    
    input [7:0] data_in;
    input wr_en,re_en,clk,reset;

    reg [7:0] mem [0:7];
    reg [3:0] wr_ptr,re_ptr;

    assign empty = (wr_ptr == re_ptr);
    assign full = (wr_ptr[2:0] == re_ptr[2:0]) && (wr_ptr[3] != re_ptr[3]) ;

    always @ (posedge clk) begin
        
        if (reset == 1) begin

            data_out <= {8'b0};
            wr_ptr <= {4'b0};
            re_ptr <= {4'b0};

            end

        else if (reset == 0) begin 
                
            if (wr_en == 1 && !full) begin

                mem [wr_ptr[2:0]] <= {data_in};
                wr_ptr <= wr_ptr + 1;

                end

            if (re_en == 1 && !empty) begin

                data_out <= {mem [re_ptr[2:0]]};
                re_ptr <= re_ptr + 1;

                end

            end

        end


endmodule

LEVEL - 2 Arithmetic Verilog HDL Problems/4. Fixed Point Restoring Divider/1. Synchronous FIFO/sync_fifo_8bit_tb.v
module synchronous_fifo_8bit_tb();

    wire [7:0] data_out;
    wire full,empty;

    reg [7:0] data_in;
    reg wr_en,re_en,clk,reset;

    integer i;

    initial clk = 1'b0;

    always #5 clk = ~clk;

    synchronous_fifo_8bit uut(data_out,full,empty,data_in,wr_en,re_en,clk,reset);

    always @ (posedge clk) begin

        #1;
        $display("t = %0t , RESET = %b , WRITE_ENABLE = %b , READ_ENABLE = %b , INPUT = %b , OUTPUT = %b , FULL = %b , EMPTY = %b",$time,reset,wr_en,re_en,data_in,data_out,full,empty);

        end

    initial begin

        $dumpfile("synchronous_fifo_8bit.vcd");
        $dumpvars(0,synchronous_fifo_8bit_tb);

        //Resetting 
        data_in=8'h00;wr_en=0;re_en=0;reset=1;#20;
        reset=0;#20;

         wr_en=1;
        
        //Writing the value 0 to 8 into the meomory
        for (i = 0; i < 8; i = i + 1) begin
            @(posedge clk);
            data_in = i; #1; 
            end

        @(posedge clk); #1;
        wr_en = 0; #20;

        //Checking if it was Writing or no
        re_en=1;#40;
        wr_en=1;data_in=8'hAA;#20;

        wr_en=0;#20;

        re_en=1;
        
        //Reading FIFO
        for(i=0; i<8 ; i=i+1) @(posedge clk);

        #10;re_en=0;#10;

        @(posedge clk);#1;re_en=1;
        @(posedge clk);#1;re_en=0;

        //Writing new values into the FIFO after reading
        @(posedge clk); #1;wr_en   = 1;data_in = 8'h11;
        @(posedge clk); #1;
        wr_en   = 0; re_en = 1; wr_en = 1;
        data_in = 8'h22;
        @(posedge clk); #1;wr_en = 0;re_en = 0;

        $finish;

    end

endmodule

LEVEL - 2 Arithmetic Verilog HDL Problems/4. Fixed Point Restoring Divider/1. Synchronous FIFO/synchronous_fifo_8bit.vcd
$date
	Fri Jul 03 23:01:12 2026
$end
$version
	Icarus Verilog
$end
$timescale
	1s
$end
$scope module synchronous_fifo_8bit_tb $end
$var wire 8 ! data_out [7:0] $end
$var wire 1 " empty $end
$var wire 1 # full $end
$var reg 1 $ clk $end
$var reg 8 % data_in [7:0] $end
$var integer 32 & i [31:0] $end
$var reg 1 ' re_en $end
$var reg 1 ( reset $end
$var reg 1 ) wr_en $end
$scope module uut $end
$var wire 1 * clk $end
$var wire 8 + data_in [7:0] $end
$var wire 1 " empty $end
$var wire 1 # full $end
$var wire 1 , re_en $end
$var wire 1 - reset $end
$var wire 1 . wr_en $end
$var reg 8 / data_out [7:0] $end
$var reg 4 0 re_ptr [3:0] $end
$var reg 4 1 wr_ptr [3:0] $end
$upscope $end
$upscope $end
$enddefinitions $end
#0
$dumpvars
bx 1
bx 0
bx /
0.
1-
0,
b0 +
0*
0)
1(
0'
bx &
b0 %
0$
x#
x"
bx !
$end
#5
0#
b0 0
1"
b0 1
b0 /
b0 !
1$
1*
#10
0$
0*
#15
1$
1*
#20
0$
0*
0(
0-
#25
1$
1*
#30
0$
0*
#35
1$
1*
#40
0$
0*
b0 &
1)
1.
#45
b1 1
0"
1$
1*
#46
b1 &
#50
0$
0*
#55
b10 1
b1 %
b1 +
1$
1*
#56
b10 &
#60
0$
0*
#65
b11 1
b10 %
b10 +
1$
1*
#66
b11 &
#70
0$
0*
#75
b100 1
b11 %
b11 +
1$
1*
#76
b100 &
#80
0$
0*
#85
b101 1
b100 %
b100 +
1$
1*
#86
b101 &
#90
0$
0*
#95
b110 1
b101 %
b101 +
1$
1*
#96
b110 &
#100
0$
0*
#105
b111 1
b110 %
b110 +
1$
1*
#106
b111 &
#110
0$
0*
#115
1#
b1000 1
b111 %
b111 +
1$
1*
#116
b1000 &
#120
0$
0*
#125
1$
1*
#126
0)
0.
#130
0$
0*
#135
1$
1*
#140
0$
0*
#145
1$
1*
#146
1'
1,
#150
0$
0*
#155
0#
b1 0
1$
1*
#160
0$
0*
#165
b10 0
b1 /
b1 !
1$
1*
#170
0$
0*
#175
b11 0
b10 /
b10 !
1$
1*
#180
0$
0*
#185
b100 0
b11 /
b11 !
1$
1*
#186
b10101010 %
b10101010 +
1)
1.
#190
0$
0*
#195
b101 0
b100 /
b100 !
b1001 1
1$
1*
#200
0$
0*
#205
b110 0
b101 /
b101 !
b1010 1
1$
1*
#206
0)
0.
#210
0$
0*
#215
b111 0
b110 /
b110 !
1$
1*
#220
0$
0*
#225
b1000 0
b111 /
b111 !
1$
1*
#226
b0 &
#230
0$
0*
#235
b1001 0
b10101010 /
b10101010 !
b1 &
1$
1*
#240
0$
0*
#245
b1010 0
1"
b10 &
1$
1*
#250
0$
0*
#255
b11 &
1$
1*
#260
0$
0*
#265
b100 &
1$
1*
#270
0$
0*
#275
b101 &
1$
1*
#280
0$
0*
#285
b110 &
1$
1*
#290
0$
0*
#295
b111 &
1$
1*
#300
0$
0*
#305
b1000 &
1$
1*
#310
0$
0*
#315
1$
1*
0'
0,
#320
0$
0*
#325
1$
1*
#326
1'
1,
#330
0$
0*
#335
1$
1*
#336
0'
0,
#340
0$
0*
#345
1$
1*
#346
b10001 %
b10001 +
1)
1.
#350
0$
0*
#355
b1011 1
0"
1$
1*
#356
b100010 %
b100010 +
1'
1,
1)
1.
#360
0$
0*
#365
b1011 0
b10001 /
b10001 !
b1100 1
1$
1*
#366
0'
0,
0)
0.
