LEVEL - 1 Verilog HDL Problems/1. 4-bit Ripple carry adder/fulladder.v
module FULLADDER(SUM,CARRY,A,B,C_in);
    output SUM;
    output CARRY;
    input A,B;
    input C_in;
    wire C0,C1,C2;
    xor(SUM,A,B,C_in);
    and(C0,A,B);
    and(C1,B,C_in);
    and(C2,A,C_in);
    or(CARRY,C0,C1,C2);
endmodule

LEVEL - 1 Verilog HDL Problems/1. 4-bit Ripple carry adder/code.v
module rippleadder(SUM,CARRY,A,B,C_in);

    output [3:0]SUM;
    output CARRY;

    input [3:0]A,B;
    input C_in;

    wire C0,C1,C2;

    FULLADDER FA0(SUM[0],C0,A[0],B[0],C_in);
    FULLADDER FA1(SUM[1],C1,A[1],B[1],C0);
    FULLADDER FA2(SUM[2],C2,A[2],B[2],C1);
    FULLADDER FA3(SUM[3],CARRY,A[3],B[3],C2);

endmodule

4-bit Ripple carry adder/testbench.v
module ripplecarrytb;

    reg [3:0]A,B;
    reg Cin;

    wire [3:0]SUM;
    wire CARRY;

    rippleadder uut(
        .SUM(SUM),
        .CARRY(CARRY),
        .A(A),
        .B(B),
        .C_in(Cin));
    
    always @ (A,B,Cin)
    begin
        #1;
        $display("A=%b, B=%b, C_in=%b || SUM=%b, CARRY=%B",A,B,Cin,SUM,CARRY);
    end

    initial begin

        $dumpfile("ripplecarryadder.vcd");
        $dumpvars(0,ripplecarrytb);

        A=4'b0000; B=4'b0000; Cin=0; #10;
        A=4'b0001; B=4'b0001; Cin=0; #10;
        A=4'b0011; B=4'b0001; Cin=0; #10;
        A=4'b0111; B=4'b0001; Cin=0; #10;
        A=4'b1010; B=4'b0101; Cin=0; #10;
        A=4'b1111; B=4'b0001; Cin=0; #10;
        A=4'b1111; B=4'b1111; Cin=0; #10;
        A=4'b1111; B=4'b1111; Cin=1; #10;


        $finish;
    end

endmodule

4-bit Ripple carry adder/ripplecarryadder.vcd
$date
	Fri Jun 26 11:25:58 2026
$end
$version
	Icarus Verilog
$end
$timescale
	1s
$end
$scope module ripplecarrytb $end
$var wire 1 ! CARRY $end
$var wire 4 " SUM [3:0] $end
$var reg 4 # A [3:0] $end
$var reg 4 $ B [3:0] $end
$var reg 1 % Cin $end
$scope module uut $end
$var wire 4 & A [3:0] $end
$var wire 4 ' B [3:0] $end
$var wire 1 ( C0 $end
$var wire 1 ) C1 $end
$var wire 1 * C2 $end
$var wire 1 ! CARRY $end
$var wire 1 + C_in $end
$var wire 4 , SUM [3:0] $end
$scope module FA0 $end
$var wire 1 - A $end
$var wire 1 . B $end
$var wire 1 / C0 $end
$var wire 1 0 C1 $end
$var wire 1 1 C2 $end
$var wire 1 ( CARRY $end
$var wire 1 + C_in $end
$var wire 1 2 SUM $end
$upscope $end
$scope module FA1 $end
$var wire 1 3 A $end
$var wire 1 4 B $end
$var wire 1 5 C0 $end
$var wire 1 6 C1 $end
$var wire 1 7 C2 $end
$var wire 1 ) CARRY $end
$var wire 1 ( C_in $end
$var wire 1 8 SUM $end
$upscope $end
$scope module FA2 $end
$var wire 1 9 A $end
$var wire 1 : B $end
$var wire 1 ; C0 $end
$var wire 1 < C1 $end
$var wire 1 = C2 $end
$var wire 1 * CARRY $end
$var wire 1 ) C_in $end
$var wire 1 > SUM $end
$upscope $end
$scope module FA3 $end
$var wire 1 ? A $end
$var wire 1 @ B $end
$var wire 1 A C0 $end
$var wire 1 B C1 $end
$var wire 1 C C2 $end
$var wire 1 ! CARRY $end
$var wire 1 * C_in $end
$var wire 1 D SUM $end
$upscope $end
$upscope $end
$upscope $end
$enddefinitions $end
#0
$dumpvars
0D
0C
0B
0A
0@
0?
0>
0=
0<
0;
0:
09
08
07
06
05
04
03
02
01
00
0/
0.
0-
b0 ,
0+
0*
0)
0(
b0 '
b0 &
0%
b0 $
b0 #
b0 "
0!
$end
#10
18
b10 "
b10 ,
1(
1/
1.
1-
b1 $
b1 '
b1 #
b1 &
#20
1>
1)
08
b100 "
b100 ,
17
13
b11 #
b11 &
#30
1D
1*
0>
b1000 "
b1000 ,
1=
19
b111 #
b111 &
#40
0*
1>
0)
18
07
0(
0!
0<
12
0/
0=
1D
b1111 "
b1111 ,
0C
1:
0-
09
1?
b101 $
b101 '
b1010 #
b1010 &
#50
1!
0D
1C
1*
0>
1=
1)
08
17
1(
02
b0 "
b0 ,
1/
0:
1-
19
b1 $
b1 '
b1111 #
b1111 &
#60
18
15
16
1>
1;
1<
1D
b1110 "
b1110 ,
1A
1B
14
1:
1@
b1111 $
b1111 '
#70
12
b1111 "
b1111 ,
10
11
1%
1+
