LEVEL - 3 Verilog HDL Problems/1. UART Transmitter/uart_tx.v
module UART_tx(tx,tx_busy,data_in,tx_start,clk,reset);

    output reg tx,tx_busy;
    input [7:0] data_in;
    input tx_start,clk,reset;

    reg [1:0] state;
    reg [2:0] bit_index;
    reg [3:0] baud_counter;

    parameter IDLE=2'b00, START=2'b01, DATA=2'b10, STOP=2'b11;
    parameter BIT_PERIOD = 16;

    always @(posedge clk) begin

        if (reset) begin
            state <= IDLE;
            tx_busy <= 1'b0;
            tx <= 1'b1;
            baud_counter <= 4'b0;
            bit_index <= 3'b0;
        end

        else begin

            case(state) 

                IDLE : begin
                    tx_busy <= 1'b0;
                    tx <= 1'b1;
                    if (tx_start && !tx_busy) begin
                        state <= START;
                        tx_busy <= 1'b1;
                    end
                end
                
                START : begin
                    tx <= 1'b0;
                    baud_counter <= baud_counter + 1'b1;
                    if (baud_counter == BIT_PERIOD - 1) begin
                        baud_counter <= 4'b0;
                        state <= DATA;
                        bit_index <= 3'b0;
                    end
                end
                
                DATA : begin
                    tx <= data_in[bit_index];
                    baud_counter <= baud_counter + 1'b1;
                    if (baud_counter == BIT_PERIOD - 1) begin
                        baud_counter <= 4'b0;
                        if (bit_index == 3'b111) begin
                            state <= STOP;
                        end
                        else bit_index <= bit_index + 1;
                    end
                end

                STOP : begin
                    tx <= 1'b1;
                    if (baud_counter == BIT_PERIOD - 1) begin
                        baud_counter <= 4'b0;
                        state <= IDLE;
                        tx_busy <= 1'b0;
                    end
                    else baud_counter <= baud_counter + 1'b1;
                end
            endcase
        end
    end
endmodule

LEVEL - 3 Verilog HDL Problems/1. UART Transmitter/uart_tx_tb.v
module UART_tx_tb();

    wire tx,tx_busy;
    reg [7:0] data_in;
    reg tx_start,clk,reset;

    UART_tx uut(tx,tx_busy,data_in,tx_start,clk,reset);

    initial clk = 0;

    always #5 clk = ~clk;
    
    initial begin

        $monitor("Time: %0t | tx: %b | tx_busy: %b | data_in: %b | tx_start: %b | clk: %b | reset: %b", $time, tx, tx_busy, data_in, tx_start, clk, reset);
        
        $dumpfile("UART_tx.vcd");
        $dumpvars(0, UART_tx_tb);

        data_in = 8'b00000000;tx_start=1'b0;reset=1'b1;#20;
        reset=1'b0;#30;

        tx_start=1'b1;data_in=8'b01001010;#30;
        tx_start=1'b0;#2000;

        tx_start=1'b1;data_in=8'b10101010;#30;
        tx_start=1'b0;#2000;
    
        $finish;
    end
endmodule

LEVEL - 3 Verilog HDL Problems/1. UART Transmitter/UART_tx.vcd
$date
	Tue Jul 07 16:43:16 2026
$end
$version
	Icarus Verilog
$end
$timescale
	1s
$end
$scope module UART_tx_tb $end
$var wire 1 ! tx $end
$var wire 1 " tx_busy $end
$var reg 1 # clk $end
$var reg 8 $ data_in [7:0] $end
$var reg 1 % reset $end
$var reg 1 & tx_start $end
$scope module uut $end
$var wire 1 ' clk $end
$var wire 8 ( data_in [7:0] $end
$var wire 1 ) reset $end
$var wire 1 * tx_start $end
$var reg 4 + baud_counter [3:0] $end
$var reg 3 , bit_index [2:0] $end
$var reg 2 - state [1:0] $end
$var reg 1 . tx $end
$var reg 1 / tx_busy $end
$upscope $end
$upscope $end
$enddefinitions $end
#0
$dumpvars
x/
x.
bx -
bx ,
bx +
0*
1)
b0 (
0'
0&
1%
b0 $
0#
x"
x!
$end
#5
b0 ,
b0 +
1.
1!
0/
0"
b0 -
1#
1'
#10
0#
0'
#15
1#
1'
#20
0#
0'
0%
0)
#25
1#
1'
#30
0#
0'
#35
1#
1'
#40
0#
0'
#45
1#
1'
#50
0#
0'
b1001010 $
b1001010 (
1&
1*
#55
1/
1"
b1 -
1#
1'
#60
0#
0'
#65
b1 +
0.
0!
1#
1'
#70
0#
0'
#75
b10 +
1#
1'
#80
0#
0'
0&
0*
#85
b11 +
1#
1'
#90
0#
0'
#95
b100 +
1#
1'
#100
0#
0'
#105
b101 +
1#
1'
#110
0#
0'
#115
b110 +
1#
1'
#120
0#
0'
#125
b111 +
1#
1'
#130
0#
0'
#135
b1000 +
1#
1'
#140
0#
0'
#145
b1001 +
1#
1'
#150
0#
0'
#155
b1010 +
1#
1'
#160
0#
0'
#165
b1011 +
1#
1'
#170
0#
0'
#175
b1100 +
1#
1'
#180
0#
0'
#185
b1101 +
1#
1'
#190
0#
0'
#195
b1110 +
1#
1'
#200
0#
0'
#205
b1111 +
1#
1'
#210
0#
0'
#215
b10 -
b0 +
1#
1'
#220
0#
0'
#225
b1 +
1#
1'
#230
0#
0'
#235
b10 +
1#
1'
#240
0#
0'
#245
b11 +
1#
1'
#250
0#
0'
#255
b100 +
1#
1'
#260
0#
0'
#265
b101 +
1#
1'
#270
0#
0'
#275
b110 +
1#
1'
#280
0#
0'
#285
b111 +
1#
1'
#290
0#
0'
#295
b1000 +
1#
1'
#300
0#
0'
#305
b1001 +
1#
1'
#310
0#
0'
#315
b1010 +
1#
1'
#320
0#
0'
#325
b1011 +
1#
1'
#330
0#
0'
#335
b1100 +
1#
1'
#340
0#
0'
#345
b1101 +
1#
1'
#350
0#
0'
#355
b1110 +
1#
1'
#360
0#
0'
#365
b1111 +
1#
1'
#370
0#
0'
#375
b1 ,
b0 +
1#
1'
#380
0#
0'
#385
b1 +
1.
1!
1#
1'
#390
0#
0'
#395
b10 +
1#
1'
#400
0#
0'
#405
b11 +
1#
1'
#410
0#
0'
#415
b100 +
1#
1'
#420
0#
0'
#425
b101 +
1#
1'
#430
0#
0'
#435
b110 +
1#
1'
#440
0#
0'
#445
b111 +
1#
1'
#450
0#
0'
#455
b1000 +
1#
1'
#460
0#
0'
#465
b1001 +
1#
1'
#470
0#
0'
#475
b1010 +
1#
1'
#480
0#
0'
#485
b1011 +
1#
1'
#490
0#
0'
#495
b1100 +
1#
1'
#500
0#
0'
#505
b1101 +
1#
1'
#510
0#
0'
#515
b1110 +
1#
1'
#520
0#
0'
#525
b1111 +
1#
1'
#530
0#
0'
#535
b10 ,
b0 +
1#
1'
#540
0#
0'
#545
b1 +
0.
0!
1#
1'
#550
0#
0'
#555
b10 +
1#
1'
#560
0#
0'
#565
b11 +
1#
1'
#570
0#
0'
#575
b100 +
1#
1'
#580
0#
0'
#585
b101 +
1#
1'
#590
0#
0'
#595
b110 +
1#
1'
#600
0#
0'
#605
b111 +
1#
1'
#610
0#
0'
#615
b1000 +
1#
1'
#620
0#
0'
#625
b1001 +
1#
1'
#630
0#
0'
#635
b1010 +
1#
1'
#640
0#
0'
#645
b1011 +
1#
1'
#650
0#
0'
#655
b1100 +
1#
1'
#660
0#
0'
#665
b1101 +
1#
1'
#670
0#
0'
#675
b1110 +
1#
1'
#680
0#
0'
#685
b1111 +
1#
1'
#690
0#
0'
#695
b11 ,
b0 +
1#
1'
#700
0#
0'
#705
b1 +
1.
1!
1#
1'
#710
0#
0'
#715
b10 +
1#
1'
#720
0#
0'
#725
b11 +
1#
1'
#730
0#
0'
#735
b100 +
1#
1'
#740
0#
0'
#745
b101 +
1#
1'
#750
0#
0'
#755
b110 +
1#
1'
#760
0#
0'
#765
b111 +
1#
1'
#770
0#
0'
#775
b1000 +
1#
1'
#780
0#
0'
#785
b1001 +
1#
1'
#790
0#
0'
#795
b1010 +
1#
1'
#800
0#
0'
#805
b1011 +
1#
1'
#810
0#
0'
#815
b1100 +
1#
1'
#820
0#
0'
#825
b1101 +
1#
1'
#830
0#
0'
#835
b1110 +
1#
1'
#840
0#
0'
#845
b1111 +
1#
1'
#850
0#
0'
#855
b100 ,
b0 +
1#
1'
#860
0#
0'
#865
b1 +
0.
0!
1#
1'
#870
0#
0'
#875
b10 +
1#
1'
#880
0#
0'
#885
b11 +
1#
1'
#890
0#
0'
#895
b100 +
1#
1'
#900
0#
0'
#905
b101 +
1#
1'
#910
0#
0'
#915
b110 +
1#
1'
#920
0#
0'
#925
b111 +
1#
1'
#930
0#
0'
#935
b1000 +
1#
1'
#940
0#
0'
#945
b1001 +
1#
1'
#950
0#
0'
#955
b1010 +
1#
1'
#960
0#
0'
#965
b1011 +
1#
1'
#970
0#
0'
#975
b1100 +
1#
1'
#980
0#
0'
#985
b1101 +
1#
1'
#990
0#
0'
#995
b1110 +
1#
1'
#1000
0#
0'
#1005
b1111 +
1#
1'
#1010
0#
0'
#1015
b101 ,
b0 +
1#
1'
#1020
0#
0'
#1025
b1 +
1#
1'
#1030
0#
0'
#1035
b10 +
1#
1'
#1040
0#
0'
#1045
b11 +
1#
1'
#1050
0#
0'
#1055
b100 +
1#
1'
#1060
0#
0'
#1065
b101 +
1#
1'
#1070
0#
0'
#1075
b110 +
1#
1'
#1080
0#
0'
#1085
b111 +
1#
1'
#1090
0#
0'
#1095
b1000 +
1#
1'
#1100
0#
0'
#1105
b1001 +
1#
1'
#1110
0#
0'
#1115
b1010 +
1#
1'
#1120
0#
0'
#1125
b1011 +
1#
1'
#1130
0#
0'
#1135
b1100 +
1#
1'
#1140
0#
0'
#1145
b1101 +
1#
1'
#1150
0#
0'
#1155
b1110 +
1#
1'
#1160
0#
0'
#1165
b1111 +
1#
1'
#1170
0#
0'
#1175
b110 ,
b0 +
1#
1'
#1180
0#
0'
#1185
b1 +
1.
1!
1#
1'
#1190
0#
0'
#1195
b10 +
1#
1'
#1200
0#
0'
#1205
b11 +
1#
1'
#1210
0#
0'
#1215
b100 +
1#
1'
#1220
0#
0'
#1225
b101 +
1#
1'
#1230
0#
0'
#1235
b110 +
1#
1'
#1240
0#
0'
#1245
b111 +
1#
1'
#1250
0#
0'
#1255
b1000 +
1#
1'
#1260
0#
0'
#1265
b1001 +
1#
1'
#1270
0#
0'
#1275
b1010 +
1#
1'
#1280
0#
0'
#1285
b1011 +
1#
1'
#1290
0#
0'
#1295
b1100 +
1#
1'
#1300
0#
0'
#1305
b1101 +
1#
1'
#1310
0#
0'
#1315
b1110 +
1#
1'
#1320
0#
0'
#1325
b1111 +
1#
1'
#1330
0#
0'
#1335
b111 ,
b0 +
1#
1'
#1340
0#
0'
#1345
b1 +
0.
0!
1#
1'
#1350
0#
0'
#1355
b10 +
1#
1'
#1360
0#
0'
#1365
b11 +
1#
1'
#1370
0#
0'
#1375
b100 +
1#
1'
#1380
0#
0'
#1385
b101 +
1#
1'
#1390
0#
0'
#1395
b110 +
1#
1'
#1400
0#
0'
#1405
b111 +
1#
1'
#1410
0#
0'
#1415
b1000 +
1#
1'
#1420
0#
0'
#1425
b1001 +
1#
1'
#1430
0#
0'
#1435
b1010 +
1#
1'
#1440
0#
0'
#1445
b1011 +
1#
1'
#1450
0#
0'
#1455
b1100 +
1#
1'
#1460
0#
0'
#1465
b1101 +
1#
1'
#1470
0#
0'
#1475
b1110 +
1#
1'
#1480
0#
0'
#1485
b1111 +
1#
1'
#1490
0#
0'
#1495
b11 -
b0 +
1#
1'
#1500
0#
0'
#1505
b1 +
1.
1!
1#
1'
#1510
0#
0'
#1515
b10 +
1#
1'
#1520
0#
0'
#1525
b11 +
1#
1'
#1530
0#
0'
#1535
b100 +
1#
1'
#1540
0#
0'
#1545
b101 +
1#
1'
#1550
0#
0'
#1555
b110 +
1#
1'
#1560
0#
0'
#1565
b111 +
1#
1'
#1570
0#
0'
#1575
b1000 +
1#
1'
#1580
0#
0'
#1585
b1001 +
1#
1'
#1590
0#
0'
#1595
b1010 +
1#
1'
#1600
0#
0'
#1605
b1011 +
1#
1'
#1610
0#
0'
#1615
b1100 +
1#
1'
#1620
0#
0'
#1625
b1101 +
1#
1'
#1630
0#
0'
#1635
b1110 +
1#
1'
#1640
0#
0'
#1645
b1111 +
1#
1'
#1650
0#
0'
#1655
0/
0"
b0 -
b0 +
1#
1'
