LEVEL - 2 FSMs Verilog HDL Problems/2. Vending Machine FSM/vending_machine.v
module vending_machine(dispense,change,coin_5,coin_10,clk,reset);

    output reg dispense,change;
    input coin_5,coin_10;
    input clk,reset;

    reg [1:0]state;

    parameter S0 = 2'b00, S5 = 2'b01, S10 = 2'b10 ;

    always @(posedge clk) begin

        if (reset)state <= S0;

        else begin

            case (state)

                S0: begin
                    dispense <= 1'b0;
                    change <= 1'b0;
                    if(coin_5 == 1'b1) state <= S5;

                    else if(coin_10 == 1'b1) state <= S10;
                end

                S5: begin
                    change <= 1'b0;
                    if(coin_5 == 1'b1) begin
                        state <= S10;
                        dispense <= 1'b0;
                    end
                    else if (coin_10 == 1'b1) begin 
                        state <= S0;
                        dispense <= 1'b1;
                    end
                end

                S10: begin
                    dispense <= 1'b1;
                    if(coin_5 == 1'b1) begin
                        state <= S0;
                        change <= 1'b0;
                    end
                    else if (coin_10 == 1'b1) begin
                        state <= S0;
                        change <= 1'b1;
                    end
                end
                
                default : begin
                    state <= S0;
                    dispense <= 1'b0;
                    change <= 1'b0;
                end
            endcase
        end
    end
endmodule

LEVEL - 2 FSMs Verilog HDL Problems/2. Vending Machine FSM/vending_machine_tb.v
module vending_machine_tb();

    wire dispense,change;
    reg coin_5,coin_10,clk,reset;

    vending_machine uut(dispense,change,coin_5,coin_10,clk,reset);

    initial clk = 1'b0;

    always #5 clk = ~clk;

    always @(posedge clk) begin

        #3;
        $display("Time = %0t , RESET = %b , COIN_5 = %b , COIN_10 = %b , DISPENSE = %b , CHANGE = %b",$time,reset,coin_5,coin_10,dispense,change);

    end

    initial begin

        $dumpfile("Vending_machine.vcd");
        $dumpvars(0,vending_machine_tb);

        coin_5 = 1'b0;coin_10 = 1'b0;reset = 1'b1;#20;
        reset = 1'b0;#20;

        //Inserting coin 5 and then coin 10
        @(posedge clk) coin_5 = 1'b1;#2;
        @(posedge clk) coin_10 = 1'b1;#20;

        coin_5 = 1'b0;coin_10 = 1'b0;#20;


        //Inserting coin 10 and then coin 5
        @(posedge clk) coin_10 = 1'b1;#2;
        @(posedge clk) coin_5 = 1'b1;#20;

        coin_5 = 1'b0;coin_10 = 1'b0;#20;

        //Inserting coin 10 and then coin 10
        @(posedge clk) coin_10 = 1'b1;#2;
        @(posedge clk) coin_10 = 1'b1;#20;

        coin_5 = 1'b0;coin_10 = 1'b0;#20;

        //Inserting three coin 5
        @(posedge clk) coin_5 = 1'b1;#2;
        @(posedge clk) coin_5 = 1'b1;#2;
        @(posedge clk) coin_5 = 1'b1;#20;

        $finish;

    end

endmodule

LEVEL - 2 FSMs Verilog HDL Problems/2. Vending Machine FSM/Vending_machine.vcd
$date
	Sat Jul 04 21:32:25 2026
$end
$version
	Icarus Verilog
$end
$timescale
	1s
$end
$scope module vending_machine_tb $end
$var wire 1 ! change $end
$var wire 1 " dispense $end
$var reg 1 # clk $end
$var reg 1 $ coin_10 $end
$var reg 1 % coin_5 $end
$var reg 1 & reset $end
$scope module uut $end
$var wire 1 ' clk $end
$var wire 1 ( coin_10 $end
$var wire 1 ) coin_5 $end
$var wire 1 * reset $end
$var reg 1 + change $end
$var reg 1 , dispense $end
$var reg 2 - state [1:0] $end
$upscope $end
$upscope $end
$enddefinitions $end
#0
$dumpvars
bx -
x,
x+
1*
0)
0(
0'
1&
0%
0$
0#
x"
x!
$end
#5
b0 -
1#
1'
#10
0#
0'
#15
1#
1'
#20
0#
0'
0&
0*
#25
0+
0!
0,
0"
1#
1'
#30
0#
0'
#35
1#
1'
#40
0#
0'
#45
b1 -
1%
1)
1#
1'
#50
0#
0'
#55
b10 -
1$
1(
1#
1'
#60
0#
0'
#65
b0 -
1,
1"
1#
1'
#70
0#
0'
#75
0,
0"
1#
1'
0$
0(
0%
0)
#80
0#
0'
#85
1#
1'
#90
0#
0'
#95
b10 -
1$
1(
1#
1'
#100
0#
0'
#105
b0 -
1,
1"
1%
1)
1#
1'
#110
0#
0'
#115
b1 -
0,
0"
1#
1'
#120
0#
0'
#125
1#
1'
0$
0(
0%
0)
#130
0#
0'
#135
1#
1'
#140
0#
0'
#145
1,
1"
b0 -
1$
1(
1#
1'
#150
0#
0'
#155
b10 -
0,
0"
1#
1'
#160
0#
0'
#165
1+
1!
b0 -
1,
1"
1#
1'
#170
0#
0'
#175
0+
0!
0,
0"
1#
1'
0$
0(
#180
0#
0'
#185
1#
1'
#190
0#
0'
#195
b1 -
1%
1)
1#
1'
#200
0#
0'
#205
b10 -
1#
1'
#210
0#
0'
#215
b0 -
1,
1"
1#
1'
#220
0#
0'
#225
b1 -
0,
0"
1#
1'
#230
0#
0'
#235
b10 -
1#
1'
