LEVEL - 1 Verilog HDL Problems/5. 4-bit universal shift register/universalsr4-bit.v
module universalsr4bit(Q,D,mode,clk,si_l,si_r);

    input [3:0] D;
    input [1:0] mode;
    input clk,si_l,si_r;

    output reg [3:0] Q;

    always @ (posedge clk)

        begin
            
            case(mode)

                2'b00: Q <= Q;
                2'b01: Q[3:0] <= {si_r,Q[3:1]};
                2'b10: Q[3:0] <= {Q[2:0],si_l};
                2'b11: Q[3:0] <= D[3:0];
                default : Q = 4'b0000;

            endcase    
         
        end

endmodule

LEVEL - 1 Verilog HDL Problems/5. 4-bit universal shift register/universalsrtb.v
module universal4bitsrtb();

    reg [3:0]D;
    reg [1:0]mode;
    reg clk,si_r,si_l;

    wire [3:0]Q;

    universalsr4bit uut(Q,D,mode,clk,si_l,si_r);

    initial clk = 0;

    always #5 clk = ~clk;

    always @(posedge clk)

        begin

            #1;
            $display("CLOCK = %b , Mode = %b , D = %b , Q = %b",clk,mode,D,Q);

        end

    initial begin

        $dumpfile("universal4bitsr.vcd");
        $dumpvars(0,universal4bitsrtb);

        // Test parallel load
        D=4'b1010; mode=2'b11; si_r=0; si_l=0; #20;

        // Test hold — Q should stay 1010
        D=4'b1111; mode=2'b00; si_r=0; si_l=0; #20;

        // Test shift right by 4 — with si_r=1
        mode=2'b01; si_r=1; si_l=0; #20;
        mode=2'b01; si_r=1; si_l=0; #20;
        mode=2'b01; si_r=1; si_l=0; #20;
        mode=2'b01; si_r=1; si_l=0; #20;

        // Test parallel load again
        D=4'b1100; mode=2'b11; si_r=0; si_l=0; #20;

        // Test shift left by 4 — with si_l=1
        mode=2'b10; si_r=0; si_l=1; #20;
        mode=2'b10; si_r=0; si_l=1; #20;
        mode=2'b10; si_r=0; si_l=1; #20;
        mode=2'b10; si_r=0; si_l=1; #20;

        $finish;

    end

endmodule

LEVEL - 1 Verilog HDL Problems/5. 4-bit universal shift register/universal4bitsr.vcd
$date
	Mon Jun 29 12:25:49 2026
$end
$version
	Icarus Verilog
$end
$timescale
	1s
$end
$scope module universal4bitsrtb $end
$var wire 4 ! Q [3:0] $end
$var reg 4 " D [3:0] $end
$var reg 1 # clk $end
$var reg 2 $ mode [1:0] $end
$var reg 1 % si_l $end
$var reg 1 & si_r $end
$scope module uut $end
$var wire 4 ' D [3:0] $end
$var wire 1 ( clk $end
$var wire 2 ) mode [1:0] $end
$var wire 1 * si_l $end
$var wire 1 + si_r $end
$var reg 4 , Q [3:0] $end
$upscope $end
$upscope $end
$enddefinitions $end
#0
$dumpvars
bx ,
0+
0*
b11 )
0(
b1010 '
0&
0%
b11 $
0#
b1010 "
bx !
$end
#5
b1010 ,
b1010 !
1#
1(
#10
0#
0(
#15
1#
1(
#20
0#
0(
b0 $
b0 )
b1111 "
b1111 '
#25
1#
1(
#30
0#
0(
#35
1#
1(
#40
0#
0(
1&
1+
b1 $
b1 )
#45
b1101 ,
b1101 !
1#
1(
#50
0#
0(
#55
b1110 ,
b1110 !
1#
1(
#60
0#
0(
#65
b1111 ,
b1111 !
1#
1(
#70
0#
0(
#75
1#
1(
#80
0#
0(
#85
1#
1(
#90
0#
0(
#95
1#
1(
#100
0#
0(
#105
1#
1(
#110
0#
0(
#115
1#
1(
#120
0#
0(
0&
0+
b11 $
b11 )
b1100 "
b1100 '
#125
b1100 ,
b1100 !
1#
1(
#130
0#
0(
#135
1#
1(
#140
0#
0(
1%
1*
b10 $
b10 )
#145
b1001 ,
b1001 !
1#
1(
#150
0#
0(
#155
b11 ,
b11 !
1#
1(
#160
0#
0(
#165
b111 ,
b111 !
1#
1(
#170
0#
0(
#175
b1111 ,
b1111 !
1#
1(
