LEVEL - 1 Verilog HDL Problems/1. 4-bit Ripple carry adder/fulladder.v
module FULLADDER(SUM,CARRY,A,B,C_in);
    output SUM;
    output CARRY;
    input A,B;
    input C_in;
    wire C0,C1,C2;
    xor(SUM,A,B,C_in);
    and(C0,A,B);
    and(C1,B,C_in);
    and(C2,A,C_in);
    or(CARRY,C0,C1,C2);
endmodule

Full Adder/FullAdder_tb.v
module FULLADDERTB;
    reg A,B,Cin;
    wire SUM,CARRY;

    FULLADDER uut(SUM,CARRY,A,B,Cin);

    always @(A, B, Cin)
        begin
            #1;
            $display("A=%b B=%b Cin=%b | SUM=%b CARRY=%b", A, B, Cin, SUM, CARRY);
        end


    initial begin
        
        $dumpfile("fulladder.vcd");
        $dumpvars(0,FULLADDERTB);

        A=0;B=0;Cin=0;#10;
        A=0;B=0;Cin=1;#10;
        A=0;B=1;Cin=0;#10;
        A=0;B=1;Cin=1;#10;
        A=1;B=0;Cin=0;#10;
        A=1;B=0;Cin=1;#10;
        A=1;B=1;Cin=0;#10;
        A=1;B=1;Cin=1;#10;

        $finish;

    end

endmodule

Full Adder/fulladder.vcd
$date
	Thu Jun 25 21:29:05 2026
$end
$version
	Icarus Verilog
$end
$timescale
	1s
$end
$scope module FULLADDERTB $end
$var wire 1 ! CARRY $end
$var wire 1 " SUM $end
$var reg 1 # A $end
$var reg 1 $ B $end
$var reg 1 % Cin $end
$scope module uut $end
$var wire 1 & A $end
$var wire 1 ' B $end
$var wire 1 ( C0 $end
$var wire 1 ) C1 $end
$var wire 1 * C2 $end
$var wire 1 ! CARRY $end
$var wire 1 + C_in $end
$var wire 1 " SUM $end
$upscope $end
$upscope $end
$enddefinitions $end
#0
$dumpvars
0+
0*
0)
0(
0'
0&
0%
0$
0#
0"
0!
$end
#10
1"
1%
1+
#20
0%
0+
1$
1'
#30
1!
0"
1)
1%
1+
#40
0!
0)
1"
0%
0+
0$
0'
1#
1&
#50
1!
0"
1*
1%
1+
#60
0*
1(
0%
0+
1$
1'
#70
1"
1)
1*
1%
1+
