LEVEL - 2 FSMs Verilog HDL Problems/4. Elevator Controller (4 Floors)/elevator_controller.v
module elevator_controller(current_floor,moving_up,moving_down,door_open,floor_0_req,floor_1_req,floor_2_req,floor_3_req,clk,reset);

    output reg [1:0]current_floor;
    output reg moving_up,moving_down,door_open;

    input floor_0_req,floor_1_req,floor_2_req,floor_3_req;
    input clk,reset;

    reg [1:0]state,target_floor,floor;
    reg [3:0]count;
    reg floor_0_latch,floor_1_latch,floor_2_latch,floor_3_latch;

    parameter IDLE=2'b00,UP=2'b01,DOWN=2'b10,DOOR=2'b11;
    parameter GROUND=2'b00,FLOOR1=2'b01,FLOOR2=2'b10,FLOOR3=2'b11;

    always @ (posedge clk) begin

        if (reset) begin
            state <= IDLE;
            target_floor <= IDLE;
            count <= 4'b0000;
            floor <= GROUND;
        end

        else  begin

            if(floor_0_req) floor_0_latch <= 1'b1;
            if(floor_1_req) floor_1_latch <= 1'b1;
            if(floor_2_req) floor_2_latch <= 1'b1;
            if(floor_3_req) floor_3_latch <= 1'b1;

            case(state)

                IDLE : begin
                    
                    current_floor <= floor;
                    moving_up <= 0;
                    moving_down <= 0;
                    door_open <= 0;

                    if (target_floor > floor) state <= UP;
                    else if (target_floor < floor) state <= DOWN ;
                    else state <= state;
    
                end

                UP : begin
                    
                    current_floor <= floor;
                    moving_up <= 1;
                    count <= count + 1;
                    if (count == 2) begin
                        count <= 4'b0000;
                        floor <= floor + 1;
                        if(floor + 1 == target_floor) begin 
                            state <= DOOR;
                            moving_up <= 0;
                        end
                        else state <= UP;
                        count <= 4'b0000;
                    end
                end

                DOWN : begin
                    
                    current_floor <= floor;
                    moving_down <= 1;
                    count <= count + 1;
                    if (count == 2) begin
                        count <= 4'b0000;
                        floor <= floor - 1;
                        if(floor - 1 == target_floor) begin 
                            state <= DOOR;
                            moving_down <= 0;
                        end
                        else state <= DOWN;
                    end
                end

                DOOR : begin
                    
                    current_floor <= floor;
                    door_open <= 1;
                    count <= count + 1;
                    if (count == 4) begin
                        state <= IDLE;
                        door_open <= 0;
                        count <= 4'b0000;

                        case (floor) 
                        
                        GROUND : floor_0_latch <= 1'b0;  
                        FLOOR1 : floor_1_latch <= 1'b0;
                        FLOOR2 : floor_2_latch <= 1'b0;
                        FLOOR3 : floor_3_latch <= 1'b0;

                        endcase
                    end
                end
            endcase
        end 
    end

    always @ (*) begin

        if (state <= IDLE) begin 
        
                case (floor) 
                        
                GROUND : begin
                    if (floor_1_latch) target_floor = FLOOR1;
                    else if (floor_2_latch) target_floor = FLOOR2;
                    else if (floor_3_latch) target_floor = FLOOR3;
                    else target_floor = floor;
                end
                        
                FLOOR1 : begin
                    if (floor_0_latch) target_floor = GROUND;
                    else if (floor_2_latch) target_floor = FLOOR2;
                    else if (floor_3_latch) target_floor = FLOOR3;
                else target_floor = floor;
                end

                FLOOR2 : begin
                    if (floor_1_latch) target_floor = FLOOR1;
                    else if (floor_3_latch) target_floor = FLOOR3;
                    else if (floor_0_latch) target_floor = GROUND;
                    else target_floor = floor;
                end

                FLOOR3 : begin
                    if (floor_2_latch) target_floor = FLOOR2;
                    else if (floor_1_latch) target_floor = FLOOR1;
                    else if (floor_0_latch) target_floor = GROUND;
                    else target_floor = floor;
                end

                default : target_floor = target_floor;
            endcase
        end
    end
endmodule

LEVEL - 2 FSMs Verilog HDL Problems/4. Elevator Controller (4 Floors)/elevator_controller_tb.v
module elevator_controller_tb();

    wire [1:0] current_floor;
    wire up,down,door;

    reg ground,first,second,third;
    reg clk,reset;

    elevator_controller uut(.current_floor(current_floor),.moving_up(up),.moving_down(down),.door_open(door),.floor_0_req(ground),.floor_1_req(first),.floor_2_req(second),.floor_3_req(third),.clk(clk),.reset(reset));

    initial clk = 0;
    always #5 clk = ~clk;

    always @(posedge clk) begin

        #2;
        $display("time = %0t , CURRENT FLOOR = %b , MOVING_UP = %b , MOVING_DOWN = %b ,DOOR = %b ,GROUND = %b ,FIRST = %b ,SECOND = %b ,THIRD = %b",$time,current_floor,up,down,door,ground,first,second,third);

    end

    initial begin 

        $dumpfile("elevator_controller(4_floor).vcd");
        $dumpvars(0,elevator_controller_tb);

        ground=0; first=0; second=0; third=0;reset=1;#20;
        reset=0;#20;

        second=1;#10;
        second=0;#150;

        ground=1; #10;
        ground=0;#150;

        first=1; third=1;#10;
        first=0; third=0;#450;

        $finish;

    end
endmodule

LEVEL - 2 FSMs Verilog HDL Problems/4. Elevator Controller (4 Floors)/elevator_controller(4_floor).vcd
$date
	Mon Jul 06 10:57:11 2026
$end
$version
	Icarus Verilog
$end
$timescale
	1s
$end
$scope module elevator_controller_tb $end
$var wire 2 ! current_floor [1:0] $end
$var wire 1 " door $end
$var wire 1 # down $end
$var wire 1 $ up $end
$var reg 1 % clk $end
$var reg 1 & first $end
$var reg 1 ' ground $end
$var reg 1 ( reset $end
$var reg 1 ) second $end
$var reg 1 * third $end
$scope module uut $end
$var wire 1 + clk $end
$var wire 1 , floor_0_req $end
$var wire 1 - floor_1_req $end
$var wire 1 . floor_2_req $end
$var wire 1 / floor_3_req $end
$var wire 1 0 reset $end
$var reg 4 1 count [3:0] $end
$var reg 2 2 current_floor [1:0] $end
$var reg 1 3 door_open $end
$var reg 2 4 floor [1:0] $end
$var reg 1 5 floor_0_latch $end
$var reg 1 6 floor_1_latch $end
$var reg 1 7 floor_2_latch $end
$var reg 1 8 floor_3_latch $end
$var reg 1 9 moving_down $end
$var reg 1 : moving_up $end
$var reg 2 ; state [1:0] $end
$var reg 2 < target_floor [1:0] $end
$upscope $end
$upscope $end
$enddefinitions $end
#0
$dumpvars
bx <
bx ;
x:
x9
x8
x7
x6
x5
bx 4
x3
bx 2
bx 1
10
0/
0.
0-
0,
0+
0*
0)
1(
0'
0&
0%
x$
x#
x"
bx !
$end
#5
b0 4
b0 1
b0 <
b0 ;
1%
1+
#10
0%
0+
#15
1%
1+
#20
0%
0+
0(
00
#25
03
0"
09
0#
0:
0$
b0 2
b0 !
1%
1+
#30
0%
0+
#35
1%
1+
#40
0%
0+
1)
1.
#45
b10 <
17
1%
1+
#50
0%
0+
0)
0.
#55
b1 ;
1%
1+
#60
0%
0+
#65
b1 1
1:
1$
1%
1+
#70
0%
0+
#75
b10 1
1%
1+
#80
0%
0+
#85
b1 4
b0 1
1%
1+
#90
0%
0+
#95
b1 1
b1 2
b1 !
1%
1+
#100
0%
0+
#105
b10 1
1%
1+
#110
0%
0+
#115
0:
0$
b11 ;
b10 4
b0 1
1%
1+
#120
0%
0+
#125
b1 1
13
1"
b10 2
b10 !
1%
1+
#130
0%
0+
#135
b10 1
1%
1+
#140
0%
0+
#145
b11 1
1%
1+
#150
0%
0+
#155
b100 1
1%
1+
#160
0%
0+
#165
07
03
0"
b0 ;
b0 1
1%
1+
#170
0%
0+
#175
1%
1+
#180
0%
0+
#185
1%
1+
#190
0%
0+
#195
1%
1+
#200
0%
0+
1'
1,
#205
b0 <
15
1%
1+
#210
0%
0+
0'
0,
#215
b10 ;
1%
1+
#220
0%
0+
#225
b1 1
19
1#
1%
1+
#230
0%
0+
#235
b10 1
1%
1+
#240
0%
0+
#245
b1 4
b0 1
1%
1+
#250
0%
0+
#255
b1 1
b1 2
b1 !
1%
1+
#260
0%
0+
#265
b10 1
1%
1+
#270
0%
0+
#275
09
0#
b11 ;
b0 4
b0 1
1%
1+
#280
0%
0+
#285
b1 1
13
1"
b0 2
b0 !
1%
1+
#290
0%
0+
#295
b10 1
1%
1+
#300
0%
0+
#305
b11 1
1%
1+
#310
0%
0+
#315
b100 1
1%
1+
#320
0%
0+
#325
05
03
0"
b0 ;
b0 1
1%
1+
#330
0%
0+
#335
1%
1+
#340
0%
0+
#345
1%
1+
#350
0%
0+
#355
1%
1+
#360
0%
0+
1*
1/
1&
1-
#365
b1 <
18
16
1%
1+
#370
0%
0+
0*
0/
0&
0-
#375
b1 ;
1%
1+
#380
0%
0+
#385
b1 1
1:
1$
1%
1+
#390
0%
0+
#395
b10 1
1%
1+
#400
0%
0+
#405
0:
0$
b11 ;
b1 4
b0 1
1%
1+
#410
0%
0+
#415
b1 1
13
1"
b1 2
b1 !
1%
1+
#420
0%
0+
#425
b10 1
1%
1+
#430
0%
0+
#435
b11 1
1%
1+
#440
0%
0+
#445
b100 1
1%
1+
#450
0%
0+
#455
b11 <
06
03
0"
b0 ;
b0 1
1%
1+
#460
0%
0+
#465
b1 ;
1%
1+
#470
0%
0+
#475
b1 1
1:
1$
1%
1+
#480
0%
0+
#485
b10 1
1%
1+
#490
0%
0+
#495
b10 4
b0 1
1%
1+
#500
0%
0+
#505
b1 1
b10 2
b10 !
1%
1+
#510
0%
0+
#515
b10 1
1%
1+
#520
0%
0+
#525
0:
0$
b11 ;
b11 4
b0 1
1%
1+
#530
0%
0+
#535
b1 1
13
1"
b11 2
b11 !
1%
1+
#540
0%
0+
#545
b10 1
1%
1+
#550
0%
0+
#555
b11 1
1%
1+
#560
0%
0+
#565
b100 1
1%
1+
#570
0%
0+
#575
08
03
0"
b0 ;
b0 1
1%
1+
