LEVEL - 2 Memory Verilog HDL Problems/2. Single-port SRAM (16x8) Behavioral Model/single_port_sram.v
module single_port_sram_16x8(data_out,data_in,wr_en,addr,cs,clk,reset);

    output reg [7:0] data_out;

    input [7:0] data_in;
    input wr_en,cs,clk,reset;
    input [3:0]addr;
    
    reg [7:0] mem [15:0];

    always @(posedge clk) begin
        
        if (reset == 1) data_out <= 8'h00;

        else if ((wr_en == 1) && (cs == 1)) mem[addr] <= data_in;

        else if ((wr_en == 0) && (cs == 1)) data_out <= mem[addr];

    end
        
endmodule

LEVEL - 2 Memory Verilog HDL Problems/2. Single-port SRAM (16x8) Behavioral Model/single_port_sram_16x8_tb.v
module single_port_sram_16x8_tb();

    wire [7:0] data_out;

    reg [7:0] data_in;
    reg wr_en,cs,clk,reset;
    reg [3:0] addr;

    single_port_sram_16x8 uut(data_out,data_in,wr_en,addr,cs,clk,reset);

    initial clk = 0 ;

    always #5 clk = ~clk;

    always @ (posedge clk) begin

        #1;
        $display("t = %0t , WE = %b , CS = %b , RESET = %b , ADDRESS = %b , INPUT = %h , OUTPUT = %h",$time,wr_en,cs,reset,addr,data_in,data_out);

        end

    initial begin 

        $dumpfile("single_port_sram_16x8.vcd");
        $dumpvars(0,single_port_sram_16x8_tb);

        data_in=8'h00;cs=0;wr_en=0;addr=4'h0;reset = 1;#20;
        reset = 0;#20

        wr_en=1;cs=1;data_in=8'hAB;addr=4'h5;#20;
        wr_en=1;cs=1;data_in=8'hCD;addr=4'hA;#20;
        wr_en=0;cs=1;addr=4'h5;#20;
        addr=4'hA;#20;
        wr_en=1;cs=0;data_in=8'h05;addr=4'h2;#20;
        wr_en=0;cs=0;addr=4'h2;#20;


        $finish;

    end

endmodule

LEVEL - 2 Memory Verilog HDL Problems/2. Single-port SRAM (16x8) Behavioral Model/single_port_sram_16x8.vcd
$date
	Sat Jul 04 11:16:11 2026
$end
$version
	Icarus Verilog
$end
$timescale
	1s
$end
$scope module single_port_sram_16x8_tb $end
$var wire 8 ! data_out [7:0] $end
$var reg 4 " addr [3:0] $end
$var reg 1 # clk $end
$var reg 1 $ cs $end
$var reg 8 % data_in [7:0] $end
$var reg 1 & reset $end
$var reg 1 ' wr_en $end
$scope module uut $end
$var wire 4 ( addr [3:0] $end
$var wire 1 ) clk $end
$var wire 1 * cs $end
$var wire 8 + data_in [7:0] $end
$var wire 1 , reset $end
$var wire 1 - wr_en $end
$var reg 8 . data_out [7:0] $end
$upscope $end
$upscope $end
$enddefinitions $end
#0
$dumpvars
bx .
0-
1,
b0 +
0*
0)
b0 (
0'
1&
b0 %
0$
0#
b0 "
bx !
$end
#5
b0 .
b0 !
1#
1)
#10
0#
0)
#15
1#
1)
#20
0#
0)
0&
0,
#25
1#
1)
#30
0#
0)
#35
1#
1)
#40
0#
0)
b101 "
b101 (
b10101011 %
b10101011 +
1$
1*
1'
1-
#45
1#
1)
#50
0#
0)
#55
1#
1)
#60
0#
0)
b1010 "
b1010 (
b11001101 %
b11001101 +
#65
1#
1)
#70
0#
0)
#75
1#
1)
#80
0#
0)
b101 "
b101 (
0'
0-
#85
b10101011 .
b10101011 !
1#
1)
#90
0#
0)
#95
1#
1)
#100
0#
0)
b1010 "
b1010 (
#105
b11001101 .
b11001101 !
1#
1)
#110
0#
0)
#115
1#
1)
#120
0#
0)
b10 "
b10 (
b101 %
b101 +
0$
0*
1'
1-
#125
1#
1)
#130
0#
0)
#135
1#
1)
#140
0#
0)
0'
0-
