LEVEL - 2 FSMs Verilog HDL Problems/3. Traffic Light Controller (4-way Intersection with Pedestrain/traffic_light_controller.v
module traffic_light_controller(road_1,road_2,ped_walk,ped_req,clk,reset);

    output reg [1:0]road_1,road_2;
    output reg ped_walk;
    input ped_req,clk,reset;

    reg [2:0] state,prev_state,count;
    reg ped_req_latch;


    parameter S0=3'b000, S1=3'b001, S2=3'b010, S3=3'b011, S4=3'b100;
    parameter RED=2'b00, GREEN=2'b01, YELLOW=2'b10;

    always @(posedge clk) begin

        if(reset == 1) begin
            state <= S0;
            prev_state <= S0;
            count <= 3'b001;
            ped_req_latch <= 1'b0;
        end

        else begin

            if (ped_req == 1'b1) ped_req_latch <= 1'b1;

            case(state)
            
                S0: begin
                    road_1 <= GREEN;
                    road_2 <= RED;
                    ped_walk <= 1'b0;
                    count <= count + 1;
                    if (count == 5 ) begin
                        count <= 3'b001;
                        state <= S1;
                    end
                end

                S1: begin
                    road_1 <= YELLOW;
                    road_2 <= RED;
                    ped_walk <= 1'b0;
                    count <= count + 1;
                    if (count == 2) begin
                        count <= 3'b001;
                        prev_state <= state;
                        state <= (ped_req_latch == 1'b1) ? S4 : S2;
                    end
                end

                S2: begin
                    road_1 <= RED;
                    road_2 <= GREEN;
                    ped_walk <= 1'b0;
                    count <= count + 1;
                    if (count == 5) begin
                        count <= 3'b001;
                        state <= S3;
                    end
                end

                S3: begin
                    road_1 <= RED;
                    road_2 <= YELLOW;
                    ped_walk <= 1'b0;
                    count <= count + 1;
                    if (count == 2) begin
                        count <= 3'b001;
                        prev_state <= state;
                        state <= (ped_req_latch== 1'b1) ? S4 : S0;
                    end
                end

                S4 : begin
                    road_1 <= RED;
                    road_2 <= RED;
                    ped_walk <= 1'b1;
                    ped_req_latch <= 1'b0;
                    count <= count + 1;
                    if (count == 4) begin
                        count <= 3'b001;
                        if (prev_state == S1) state <= S2;
                        else state <= S0;
                    end
                end
            endcase
        end
    end
endmodule

LEVEL - 2 FSMs Verilog HDL Problems/3. Traffic Light Controller (4-way Intersection with Pedestrain/traffic_light_controller_tb.v
module traffic_light_controller_tb();

    wire [1:0] road_1,road_2;
    wire ped_walk;

    reg ped_req,clk,reset;

    initial clk = 1'b0;

    traffic_light_controller dut(road_1,road_2,ped_walk,ped_req,clk,reset);

    always #5 clk = ~clk;

    always @(posedge clk) begin
        
        #2;
        $display("Time = %0t , RESET = %b , ROAD_1 = %b , ROAD_2 = %b , PED_WALK = %b , PED_REQ = %b ",$time,reset,road_1,road_2,ped_walk,ped_req);
    end

    initial begin

        $dumpfile("traffic_light_controller.vcd");
        $dumpvars(0,traffic_light_controller_tb);

        ped_req=1'b0;reset=1'b1;#10;
        reset=1'b0;#100;

        ped_req=1'b1;#20;
        ped_req=1'b0;#20;

        ped_req=1'b1;#50;
        ped_req=1'b0;#80;

        $finish;
    end
endmodule

LEVEL - 2 FSMs Verilog HDL Problems/3. Traffic Light Controller (4-way Intersection with Pedestrain/traffic_light_controller.vcd
$date
	Sat Jul 04 22:34:48 2026
$end
$version
	Icarus Verilog
$end
$timescale
	1s
$end
$scope module traffic_light_controller_tb $end
$var wire 1 ! ped_walk $end
$var wire 2 " road_1 [1:0] $end
$var wire 2 # road_2 [1:0] $end
$var reg 1 $ clk $end
$var reg 1 % ped_req $end
$var reg 1 & reset $end
$scope module dut $end
$var wire 1 ' clk $end
$var wire 1 ( ped_req $end
$var wire 1 ) reset $end
$var reg 3 * count [2:0] $end
$var reg 1 + ped_req_latch $end
$var reg 1 , ped_walk $end
$var reg 3 - prev_state [2:0] $end
$var reg 2 . road_1 [1:0] $end
$var reg 2 / road_2 [1:0] $end
$var reg 3 0 state [2:0] $end
$upscope $end
$upscope $end
$enddefinitions $end
#0
$dumpvars
bx 0
bx /
bx .
bx -
x,
x+
bx *
1)
0(
0'
1&
0%
0$
bx #
bx "
x!
$end
#5
0+
b1 *
b0 -
b0 0
1$
1'
#10
0$
0'
0&
0)
#15
b10 *
0,
0!
b0 /
b0 #
b1 .
b1 "
1$
1'
#20
0$
0'
#25
b11 *
1$
1'
#30
0$
0'
#35
b100 *
1$
1'
#40
0$
0'
#45
b101 *
1$
1'
#50
0$
0'
#55
b1 0
b1 *
1$
1'
#60
0$
0'
#65
b10 *
b10 .
b10 "
1$
1'
#70
0$
0'
#75
b10 0
b1 -
b1 *
1$
1'
#80
0$
0'
#85
b10 *
b1 /
b1 #
b0 .
b0 "
1$
1'
#90
0$
0'
#95
b11 *
1$
1'
#100
0$
0'
#105
b100 *
1$
1'
#110
0$
0'
1%
1(
#115
b101 *
1+
1$
1'
#120
0$
0'
#125
b11 0
b1 *
1$
1'
#130
0$
0'
0%
0(
#135
b10 *
b10 /
b10 #
1$
1'
#140
0$
0'
#145
b100 0
b11 -
b1 *
1$
1'
#150
0$
0'
1%
1(
#155
b10 *
0+
1,
1!
b0 /
b0 #
1$
1'
#160
0$
0'
#165
b11 *
0+
1$
1'
#170
0$
0'
#175
b100 *
0+
1$
1'
#180
0$
0'
#185
b0 0
b1 *
0+
1$
1'
#190
0$
0'
#195
b10 *
0,
0!
b1 .
b1 "
1+
1$
1'
#200
0$
0'
0%
0(
#205
b11 *
1$
1'
#210
0$
0'
#215
b100 *
1$
1'
#220
0$
0'
#225
b101 *
1$
1'
#230
0$
0'
#235
b1 0
b1 *
1$
1'
#240
0$
0'
#245
b10 *
b10 .
b10 "
1$
1'
#250
0$
0'
#255
b100 0
b1 -
b1 *
1$
1'
#260
0$
0'
#265
b10 *
0+
1,
1!
b0 .
b0 "
1$
1'
#270
0$
0'
#275
b11 *
1$
1'
