LEVEL - 2 Arithmetic Verilog HDL Problems/1. 8-bit ALU with 8 operations/alu8bit.v
module alu8bitwith8operations(ALU_out,A,B,ALU_Sel,carry,zero);

    output reg [7:0] ALU_out;
    output reg carry;
    output wire zero;
    input [7:0] A,B;
    input [2:0] ALU_Sel;

    assign zero = (ALU_out == 8'b00000000);

    always @(*) begin

        case(ALU_Sel)

            3'b000: {carry,ALU_out} = A + B; 
            3'b001: {carry,ALU_out} = A - B; 
            3'b010: ALU_out = A & B;         
            3'b011: ALU_out = A | B;      
            3'b100: ALU_out = A ^ B;         
            3'b101: ALU_out = ~A;             
            3'b110: ALU_out = A << 1;        
            3'b111: ALU_out = A >> 1;        

            default: ALU_out = 8'b00000000;

        endcase

    end

endmodule

LEVEL - 2 Arithmetic Verilog HDL Problems/1. 8-bit ALU with 8 operations/alu8bitw8oprtb.v
module alu8bitwith8operations_tb();

    reg [7:0] A,B;
    reg [2:0] ALU_Sel;
    wire [7:0] ALU_out;
    wire carry;
    wire zero;

    alu8bitwith8operations uut(ALU_out,A,B,ALU_Sel,carry,zero);

    always @ (A,B,ALU_Sel,ALU_out,zero) begin

        #1;
        $display("A = %b , B = %b , OPERATION = %b , OUTPUT = %b , CARRY = %b , ZERO = %b",A,B,ALU_Sel,ALU_out,carry,zero);

    end

    initial begin

        $dumpfile("alu8bitwith8operations.vcd");
        $dumpvars(0,alu8bitwith8operations_tb);
        
        A=8'b10101010; B=8'b01010101; ALU_Sel=3'b000; #10; // ADD
        A=8'b10101010; B=8'b01010101; ALU_Sel=3'b001; #10; // SUB
        A=8'b10101010; B=8'b01010101; ALU_Sel=3'b010; #10; // AND
        A=8'b10101010; B=8'b01010101; ALU_Sel=3'b011; #10; // OR
        A=8'b10101010; B=8'b01010101; ALU_Sel=3'b100; #10; // XOR
        A=8'b10101010; B=8'b01010101; ALU_Sel=3'b101; #10; // NOT
        A=8'b10101010; B=8'b01010101; ALU_Sel=3'b110; #10; // SHL
        A=8'b10101010; B=8'b01010101; ALU_Sel=3'b111; #10; // SHR
        A=8'b00000001; B=8'b00000010; ALU_Sel=3'b001; #10; 

        $finish;

    end

endmodule

LEVEL - 2 Arithmetic Verilog HDL Problems/1. 8-bit ALU with 8 operations/alu8bitwith8operations.vcd
$date
	Mon Jun 29 19:52:31 2026
$end
$version
	Icarus Verilog
$end
$timescale
	1s
$end
$scope module alu8bitwith8operations_tb $end
$var wire 8 ! ALU_out [7:0] $end
$var wire 1 " carry $end
$var wire 1 # zero $end
$var reg 8 $ A [7:0] $end
$var reg 3 % ALU_Sel [2:0] $end
$var reg 8 & B [7:0] $end
$scope module uut $end
$var wire 8 ' A [7:0] $end
$var wire 3 ( ALU_Sel [2:0] $end
$var wire 8 ) B [7:0] $end
$var wire 1 # zero $end
$var reg 8 * ALU_out [7:0] $end
$var reg 1 + carry $end
$upscope $end
$upscope $end
$enddefinitions $end
#0
$dumpvars
0+
b11111111 *
b1010101 )
b0 (
b10101010 '
b1010101 &
b0 %
b10101010 $
0#
0"
b11111111 !
$end
#10
b1010101 *
b1010101 !
b1 %
b1 (
#20
b0 *
1#
b0 !
b10 %
b10 (
#30
b11111111 *
0#
b11111111 !
b11 %
b11 (
#40
b100 %
b100 (
#50
b1010101 *
b1010101 !
b101 %
b101 (
#60
b1010100 *
b1010100 !
b110 %
b110 (
#70
b1010101 *
b1010101 !
b111 %
b111 (
#80
1+
1"
b11111111 *
b11111111 !
b1 %
b1 (
b10 &
b10 )
b1 $
b1 '
