LEVEL - 2 Memory Verilog HDL Problems/3. Dual-port RAM with Collision Detection/dualportram.v
module dual_port_ram_16x8(data_out_a,data_out_b,collision,data_in_a,data_in_b,addr_a,addr_b,we_a,we_b,clk,reset);

    output reg [7:0] data_out_a,data_out_b;
    output wire collision;

    input [7:0] data_in_a,data_in_b;
    input [3:0] addr_a,addr_b;
    input we_a,we_b,clk,reset;

    reg [7:0] mem [15:0];

    assign collision = ((addr_a == addr_b) && (we_a || we_b));

    always @(posedge clk) begin

        if (reset == 1) begin

            data_out_a <= 8'h00;
            data_out_b <= 8'h00;

        end

        else if (!collision) begin

            if (we_a) mem[addr_a] <= data_in_a;
            
            else data_out_a <= mem[addr_a];

            if (we_b) mem[addr_b] <= data_in_b;

            else data_out_b <= mem[addr_b];

        end

        else if (collision) begin

            if (!we_a) data_out_a <= mem[addr_a];

            if (!we_b) data_out_b <= mem[addr_b];

        end
        
    end

endmodule

LEVEL - 2 Memory Verilog HDL Problems/3. Dual-port RAM with Collision Detection/dualportram_tb.v
module dual_port_ram_16x8_tb();

    wire [7:0] data_out_a,data_out_b;
    wire collision;

    reg [7:0] data_in_a,data_in_b;
    reg [3:0] addr_a,addr_b;
    reg we_a,we_b,clk,reset;

    dual_port_ram_16x8 uut(data_out_a,data_out_b,collision,data_in_a,data_in_b,addr_a,addr_b,we_a,we_b,clk,reset);

    initial clk = 0;

    always #5 clk = ~clk;

    always @(posedge clk) begin

        #1;
        $display("t = %0t, RESET = %b , WRITE_A = %b , INPUT_A = %h , ADDRESS_A = %h , OUTPUT_A = %h ",$time,reset,we_a,data_in_a,addr_a,data_out_a);
        $display("t = %0t, RESET = %b , WRITE_B = %b , INPUT_B = %h , ADDRESS_B = %h , OUTPUT_B = %h ",$time,reset,we_b,data_in_b,addr_b,data_out_b);
        
    end

    initial begin 

        $dumpfile("dual_port_ram_16x8.vcd");
        $dumpvars(0,dual_port_ram_16x8_tb);

        data_in_a=8'h00;we_a=0;addr_a=4'h0;data_in_b=8'h00;we_b=0;addr_b=0;reset=1;#20;

        reset=0;#20;

        data_in_a=8'hAA;we_a=1;addr_a=4'h5;
        data_in_b=8'hBB;we_b=1;addr_b=4'h3;#20

        data_in_a=8'hBC;addr_a=4'h6;
        data_in_b=8'hFF;addr_b=4'h0;#20;

        data_in_b=8'hEE;addr_b=4'hA;#20;

        we_a=0;we_b=0;#20;

        addr_a=4'h3;addr_b=4'h6;#20;

        addr_a=4'h5;addr_b=4'h5;#20;

        addr_a=4'h0;#20;

        $finish;

    end

endmodule

LEVEL - 2 Memory Verilog HDL Problems/3. Dual-port RAM with Collision Detection/dual_port_ram_16x8.vcd
$date
	Sat Jul 04 12:27:08 2026
$end
$version
	Icarus Verilog
$end
$timescale
	1s
$end
$scope module dual_port_ram_16x8_tb $end
$var wire 1 ! collision $end
$var wire 8 " data_out_a [7:0] $end
$var wire 8 # data_out_b [7:0] $end
$var reg 4 $ addr_a [3:0] $end
$var reg 4 % addr_b [3:0] $end
$var reg 1 & clk $end
$var reg 8 ' data_in_a [7:0] $end
$var reg 8 ( data_in_b [7:0] $end
$var reg 1 ) reset $end
$var reg 1 * we_a $end
$var reg 1 + we_b $end
$scope module uut $end
$var wire 4 , addr_a [3:0] $end
$var wire 4 - addr_b [3:0] $end
$var wire 1 . clk $end
$var wire 1 ! collision $end
$var wire 8 / data_in_a [7:0] $end
$var wire 8 0 data_in_b [7:0] $end
$var wire 1 1 reset $end
$var wire 1 2 we_a $end
$var wire 1 3 we_b $end
$var reg 8 4 data_out_a [7:0] $end
$var reg 8 5 data_out_b [7:0] $end
$upscope $end
$upscope $end
$enddefinitions $end
#0
$dumpvars
bx 5
bx 4
03
02
11
b0 0
b0 /
0.
b0 -
b0 ,
0+
0*
1)
b0 (
b0 '
0&
b0 %
b0 $
bx #
bx "
0!
$end
#5
b0 5
b0 #
b0 4
b0 "
1&
1.
#10
0&
0.
#15
1&
1.
#20
0&
0.
0)
01
#25
bx 5
bx #
bx 4
bx "
1&
1.
#30
0&
0.
#35
1&
1.
#40
0&
0.
b11 %
b11 -
1+
13
b10111011 (
b10111011 0
b101 $
b101 ,
1*
12
b10101010 '
b10101010 /
#45
1&
1.
#50
0&
0.
#55
1&
1.
#60
0&
0.
b0 %
b0 -
b11111111 (
b11111111 0
b110 $
b110 ,
b10111100 '
b10111100 /
#65
1&
1.
#70
0&
0.
#75
1&
1.
#80
0&
0.
b1010 %
b1010 -
b11101110 (
b11101110 0
#85
1&
1.
#90
0&
0.
#95
1&
1.
#100
0&
0.
0+
03
0*
02
#105
b11101110 5
b11101110 #
b10111100 4
b10111100 "
1&
1.
#110
0&
0.
#115
1&
1.
#120
0&
0.
b110 %
b110 -
b11 $
b11 ,
#125
b10111100 5
b10111100 #
b10111011 4
b10111011 "
1&
1.
#130
0&
0.
#135
1&
1.
#140
0&
0.
b101 %
b101 -
b101 $
b101 ,
#145
b10101010 5
b10101010 #
b10101010 4
b10101010 "
1&
1.
#150
0&
0.
#155
1&
1.
#160
0&
0.
b0 $
b0 ,
#165
b11111111 4
b11111111 "
1&
1.
