LEVEL - 1 Verilog HDL Problems/4. D flip-flop/dflip-flop.v
module dflipflop(Q,D,reset,clk,enable);

    output reg Q;
    input D,reset,clk,enable;

    always @ (posedge clk)

        begin
            
            if (reset==1) Q = 1'b0;

            else if (enable==1) Q = D;

            else Q = Q;
            
        end

endmodule

LEVEL - 1 Verilog HDL Problems/4. D flip-flop/dflipfloptb.v
module dflipfloptb();

    reg D,clk,reset,enable;
    wire Q;

    dflipflop uut(.Q(Q),.D(D),.reset(reset),.clk(clk),.enable(enable));

    initial clk = 0;

    always #5 clk=~clk;

    always @ (posedge clk)

        begin

            #1;
            $display("CLOCK = %b , RESET = %b ' ENABLE = %b , D = %b , Q = %b",clk,reset,enable,D,Q);

        end
    
    initial begin

        $dumpfile("dflipflop.vcd");
        $dumpvars(0,dflipfloptb);

        reset=1;enable=0;D=0;#20;
        reset=0;enable=1;D=1;#20;
        reset=0;enable=1;D=0;#20;
        reset=0;enable=0;D=1;#20;
        reset=1;enable=1;D=1;#20;

        $finish;

    end

endmodule

LEVEL - 1 Verilog HDL Problems/4. D flip-flop/dflipflop.vcd
$date
	Mon Jun 29 11:28:25 2026
$end
$version
	Icarus Verilog
$end
$timescale
	1s
$end
$scope module dflipfloptb $end
$var wire 1 ! Q $end
$var reg 1 " D $end
$var reg 1 # clk $end
$var reg 1 $ enable $end
$var reg 1 % reset $end
$scope module uut $end
$var wire 1 & D $end
$var wire 1 ' clk $end
$var wire 1 ( enable $end
$var wire 1 ) reset $end
$var reg 1 * Q $end
$upscope $end
$upscope $end
$enddefinitions $end
#0
$dumpvars
x*
1)
0(
0'
0&
1%
0$
0#
0"
x!
$end
#5
0*
0!
1#
1'
#10
0#
0'
#15
1#
1'
#20
0#
0'
1"
1&
1$
1(
0%
0)
#25
1*
1!
1#
1'
#30
0#
0'
#35
1#
1'
#40
0#
0'
0"
0&
#45
0*
0!
1#
1'
#50
0#
0'
#55
1#
1'
#60
0#
0'
1"
1&
0$
0(
#65
1#
1'
#70
0#
0'
#75
1#
1'
#80
0#
0'
1$
1(
1%
1)
