LEVEL - 2 Arithmetic Verilog HDL Problems/4. Fixed Point Restoring Divider/fixedpointrestoringdivider.v
module fixedpoint_restoringdivider(Quotient,Remainder,Done,Dividend,Divider,reset,clk,start);

    output reg [7:0] Quotient;
    output reg [3:0] Remainder;
    output reg Done;

    input [7:0] Dividend;
    input [3:0] Divider;
    input reset,clk,start;

    reg [7:0] Q;
    reg [4:0] M;
    reg [4:0] PR;
    reg [3:0] counter;
    reg state;

    localparam SHIFT = 1'b0, SUB = 1'b1 ;

    always @ (posedge clk) begin
        
        if (reset == 1) begin

            PR <= 5'b00000;
            Done <= 1'b0;
            Q <= 8'b00000000;
            counter <= 4'b0000;
            Quotient <= 8'b00000000;
            Remainder <= 4'b0000;

        end

        else if (start == 1 ) begin

            PR <= 5'b00000;
            Done <= 1'b0;
            counter <= 4'b0000;
            Q <= {Dividend};
            M <= {1'b0,Divider};
            state <= SHIFT;

        end

        else if (!Done ) begin
            
            case(state)

            SHIFT : begin 
                {PR,Q} <= {PR[3:0],Q,1'b0};
                state <= SUB;
            end

            SUB : begin

                if (PR >= M) begin
                    PR <= PR - M;
                    Q[0] <= 1'b1;
                end

                else begin
                    PR <= PR;
                    Q[0] <= 1'b0;
                end

                counter <= counter + 1;
                state <= SHIFT;

                if (counter ==7) begin 
                    Quotient <= Q;
                    Remainder <= {PR[3:0]};
                    Done <= 1;
                end

            end

            endcase

        end

        else if (Done == 1) begin 
            Quotient <= Q;
            Remainder <= {PR[3:0]};

        end

    end

endmodule

LEVEL - 2 Arithmetic Verilog HDL Problems/4. Fixed Point Restoring Divider/fixedpointrestoring_register_tb.v
module fixedpoint_restoringdivider_tb();

    reg [7:0]A;
    reg [3:0]B;
    reg reset,clk,start;

    wire [7:0]Q;
    wire [3:0]R;

    wire done;

    fixedpoint_restoringdivider uut(.Quotient(Q),.Remainder(R),.Done(done),.Dividend(A),.Divider(B),.reset(reset),.clk(clk),.start(start));

    initial clk = 0;

    always #5 clk = ~clk;

    always @ (posedge done) begin

        #1;
        $display("DIVIDEND = %b , DIVIDER = %b || QUOTIENT = %b , REMAINDER = %b",A,B,Q,R);
    end

    initial begin

        $dumpfile("fixed_point_restoring_divider.vcd");
        $dumpvars(0,fixedpoint_restoringdivider_tb);

        A=8'b00000000;B=4'b0000;reset=1'b1;#10;
        reset=1'b0;#10;
        A=8'b11001000;B=4'b1100;start=1'b1;#10;
        start=1'b0;#20

        wait (done);#20;

        A=8'b01100100;B=4'b1010;start=1'b1;#30;
        start=1'b0;#10;

        wait (done);#20;

        $finish;

    end

endmodule

LEVEL - 2 Arithmetic Verilog HDL Problems/4. Fixed Point Restoring Divider/fixed_point_restoring_divider.vcd
$date
	Fri Jul 03 11:21:58 2026
$end
$version
	Icarus Verilog
$end
$timescale
	1s
$end
$scope module fixedpoint_restoringdivider_tb $end
$var wire 8 ! Q [7:0] $end
$var wire 4 " R [3:0] $end
$var wire 1 # done $end
$var reg 8 $ A [7:0] $end
$var reg 4 % B [3:0] $end
$var reg 1 & clk $end
$var reg 1 ' reset $end
$var reg 1 ( start $end
$scope module uut $end
$var wire 8 ) Dividend [7:0] $end
$var wire 4 * Divider [3:0] $end
$var wire 1 + clk $end
$var wire 1 , reset $end
$var wire 1 - start $end
$var reg 1 . Done $end
$var reg 5 / M [4:0] $end
$var reg 5 0 PR [4:0] $end
$var reg 8 1 Q [7:0] $end
$var reg 8 2 Quotient [7:0] $end
$var reg 4 3 Remainder [3:0] $end
$var reg 4 4 counter [3:0] $end
$var reg 1 5 state $end
$upscope $end
$upscope $end
$enddefinitions $end
#0
$dumpvars
x5
bx 4
bx 3
bx 2
bx 1
bx 0
bx /
x.
x-
1,
0+
b0 *
b0 )
x(
1'
0&
b0 %
b0 $
x#
bx "
bx !
$end
#5
b0 3
b0 "
b0 2
b0 !
b0 4
b0 1
0.
0#
b0 0
1&
1+
#10
0&
0+
0'
0,
#15
1&
1+
#20
0&
0+
1(
1-
b1100 %
b1100 *
b11001000 $
b11001000 )
#25
05
b1100 /
b11001000 1
1&
1+
#30
0&
0+
0(
0-
#35
15
b1 0
b10010000 1
1&
1+
#40
0&
0+
#45
05
b1 4
b10010000 1
1&
1+
#50
0&
0+
#55
15
b11 0
b100000 1
1&
1+
#60
0&
0+
#65
05
b10 4
b100000 1
1&
1+
#70
0&
0+
#75
15
b110 0
b1000000 1
1&
1+
#80
0&
0+
#85
05
b11 4
b1000000 1
1&
1+
#90
0&
0+
#95
15
b1100 0
b10000000 1
1&
1+
#100
0&
0+
#105
05
b100 4
b10000001 1
b0 0
1&
1+
#110
0&
0+
#115
15
b1 0
b10 1
1&
1+
#120
0&
0+
#125
05
b101 4
b10 1
1&
1+
#130
0&
0+
#135
15
b10 0
b100 1
1&
1+
#140
0&
0+
#145
05
b110 4
b100 1
1&
1+
#150
0&
0+
#155
15
b100 0
b1000 1
1&
1+
#160
0&
0+
#165
05
b111 4
b1000 1
1&
1+
#170
0&
0+
#175
15
b1000 0
b10000 1
1&
1+
#180
0&
0+
#185
1.
1#
b1000 3
b1000 "
b10000 2
b10000 !
05
b1000 4
b10000 1
1&
1+
#190
0&
0+
#195
1&
1+
#200
0&
0+
#205
b1010 /
b1100100 1
b0 4
0.
0#
b0 0
1&
1+
1(
1-
b1010 %
b1010 *
b1100100 $
b1100100 )
#210
0&
0+
#215
1&
1+
#220
0&
0+
#225
1&
1+
#230
0&
0+
#235
15
b11001000 1
1&
1+
0(
0-
#240
0&
0+
#245
05
b1 4
b11001000 1
1&
1+
#250
0&
0+
#255
15
b1 0
b10010000 1
1&
1+
#260
0&
0+
#265
05
b10 4
b10010000 1
1&
1+
#270
0&
0+
#275
15
b11 0
b100000 1
1&
1+
#280
0&
0+
#285
05
b11 4
b100000 1
1&
1+
#290
0&
0+
#295
15
b110 0
b1000000 1
1&
1+
#300
0&
0+
#305
05
b100 4
b1000000 1
1&
1+
#310
0&
0+
#315
15
b1100 0
b10000000 1
1&
1+
#320
0&
0+
#325
05
b101 4
b10000001 1
b10 0
1&
1+
#330
0&
0+
#335
15
b101 0
b10 1
1&
1+
#340
0&
0+
#345
05
b110 4
b10 1
1&
1+
#350
0&
0+
#355
15
b1010 0
b100 1
1&
1+
#360
0&
0+
#365
05
b111 4
b101 1
b0 0
1&
1+
#370
0&
0+
#375
15
b1010 1
1&
1+
#380
0&
0+
#385
1.
1#
b0 3
b0 "
b1010 2
b1010 !
05
b1000 4
b1010 1
1&
1+
