LEVEL - 3 Verilog HDL Problems/2. UART Receiver/uart_rx.v
module UART_rx(rx_data,rx_done,rx,clk,reset);

    output reg [7:0] rx_data;
    output reg rx_done;

    input rx,clk,reset;

    reg [1:0] state;
    reg [2:0] bit_index;
    reg [3:0] baud_counter;

    reg prev_rx;

    parameter IDLE=2'b00, START=2'b01, DATA=2'b10, STOP=2'b11;
    parameter BIT_PERIOD = 16;

    always @(posedge clk) begin

        if (reset) begin
            rx_data <= 8'b0;
            rx_done <= 0;
            baud_counter <= 4'b0;
            state <= IDLE;
        end

        else begin
            
            case (state)

            IDLE : begin
                rx_done <= 0;
                prev_rx <= rx;
                if (prev_rx == 1 && rx == 0 && !rx_done) state <= START;
            end

            START : begin
                baud_counter <= baud_counter + 1;
                prev_rx <= rx;
                if (baud_counter == (BIT_PERIOD/2)) begin
                    baud_counter <= 4'b0;
                    bit_index <= 3'b0;
                    state <= DATA;
                end 
            end

            DATA : begin
                baud_counter <= baud_counter + 1;
                prev_rx <= rx;
                if (baud_counter == BIT_PERIOD - 1) begin
                    baud_counter <= 0;
                    rx_data[bit_index] <= rx;
                    if (bit_index == 3'b111) state <= STOP;
                    else bit_index <= bit_index + 1;
                end
            end

            STOP : begin
                rx_done <= 1;
                prev_rx <= rx;
                baud_counter <= baud_counter + 1;
                if (baud_counter == BIT_PERIOD - 1) begin
                    baud_counter <= 4'b0;
                    state <= IDLE;
                    rx_data <= {8'b0};
                end
            end
            endcase
        end
    end
endmodule

LEVEL - 3 Verilog HDL Problems/2. UART Receiver/uart_rx_tb.v
module UART_rx_tb();

    wire [7:0] rx_data;
    wire rx_done;

    reg rx,clk,reset;

    UART_rx uut(rx_data,rx_done,rx,clk,reset);

    initial clk = 0;

    always #5 clk = ~clk;

    initial begin 

        $monitor("Time = %0t | CLOCK = %b | RESET = %b | rx = %b | rx_data = %b | rx_done %b",$time,clk,reset,rx,rx_data,rx_done);

        $dumpfile("UART_rx.vcd");
        $dumpvars(0,UART_rx_tb);

        rx=0;reset=1;#30;
        reset=0;#20;

        //one
        rx = 1;#160;
        rx = 0;#160;

        rx = 0;#160;
        rx = 1;#160;
        rx = 1;#160;
        rx = 0;#160;
        rx = 1;#160;
        rx = 1;#160;
        rx = 0;#160;
        rx = 1;#160;

        //two
        rx = 1;#160;
        rx = 0;#160;

        rx = 1;#160;
        rx = 1;#160;
        rx = 1;#160;
        rx = 1;#160;
        rx = 1;#160;
        rx = 1;#160;
        rx = 1;#160;
        rx = 1;#160;

        //three
        rx = 1;#160;
        rx = 0;#160;

        rx = 1;#160;
        rx = 0;#160;
        rx = 1;#160;
        rx = 1;#160;
        rx = 0;#160;
        rx = 0;#160;
        rx = 1;#160;
        rx = 0;#160;

        $finish;

    end
endmodule

LEVEL - 3 Verilog HDL Problems/2. UART Receiver/UART_rx.vcd
$date
	Tue Jul 07 17:49:24 2026
$end
$version
	Icarus Verilog
$end
$timescale
	1s
$end
$scope module UART_rx_tb $end
$var wire 8 ! rx_data [7:0] $end
$var wire 1 " rx_done $end
$var reg 1 # clk $end
$var reg 1 $ reset $end
$var reg 1 % rx $end
$scope module uut $end
$var wire 1 & clk $end
$var wire 1 ' reset $end
$var wire 1 ( rx $end
$var reg 4 ) baud_counter [3:0] $end
$var reg 3 * bit_index [2:0] $end
$var reg 1 + prev_rx $end
$var reg 8 , rx_data [7:0] $end
$var reg 1 - rx_done $end
$var reg 2 . state [1:0] $end
$upscope $end
$upscope $end
$enddefinitions $end
#0
$dumpvars
bx .
x-
bx ,
x+
bx *
bx )
0(
1'
0&
0%
1$
0#
x"
bx !
$end
#5
b0 .
b0 )
0-
0"
b0 ,
b0 !
1#
1&
#10
0#
0&
#15
1#
1&
#20
0#
0&
#25
1#
1&
#30
0#
0&
0$
0'
#35
0+
1#
1&
#40
0#
0&
#45
1#
1&
#50
0#
0&
1%
1(
#55
1+
1#
1&
#60
0#
0&
#65
1#
1&
#70
0#
0&
#75
1#
1&
#80
0#
0&
#85
1#
1&
#90
0#
0&
#95
1#
1&
#100
0#
0&
#105
1#
1&
#110
0#
0&
#115
1#
1&
#120
0#
0&
#125
1#
1&
#130
0#
0&
#135
1#
1&
#140
0#
0&
#145
1#
1&
#150
0#
0&
#155
1#
1&
#160
0#
0&
#165
1#
1&
#170
0#
0&
#175
1#
1&
#180
0#
0&
#185
1#
1&
#190
0#
0&
#195
1#
1&
#200
0#
0&
#205
1#
1&
#210
0#
0&
0%
0(
#215
b1 .
0+
1#
1&
#220
0#
0&
#225
b1 )
1#
1&
#230
0#
0&
#235
b10 )
1#
1&
#240
0#
0&
#245
b11 )
1#
1&
#250
0#
0&
#255
b100 )
1#
1&
#260
0#
0&
#265
b101 )
1#
1&
#270
0#
0&
#275
b110 )
1#
1&
#280
0#
0&
#285
b111 )
1#
1&
#290
0#
0&
#295
b1000 )
1#
1&
#300
0#
0&
#305
b10 .
b0 *
b0 )
1#
1&
#310
0#
0&
#315
b1 )
1#
1&
#320
0#
0&
#325
b10 )
1#
1&
#330
0#
0&
#335
b11 )
1#
1&
#340
0#
0&
#345
b100 )
1#
1&
#350
0#
0&
#355
b101 )
1#
1&
#360
0#
0&
#365
b110 )
1#
1&
#370
0#
0&
#375
b111 )
1#
1&
#380
0#
0&
#385
b1000 )
1#
1&
#390
0#
0&
#395
b1001 )
1#
1&
#400
0#
0&
#405
b1010 )
1#
1&
#410
0#
0&
#415
b1011 )
1#
1&
#420
0#
0&
#425
b1100 )
1#
1&
#430
0#
0&
#435
b1101 )
1#
1&
#440
0#
0&
#445
b1110 )
1#
1&
#450
0#
0&
#455
b1111 )
1#
1&
#460
0#
0&
#465
b1 *
b0 ,
b0 )
1#
1&
#470
0#
0&
#475
b1 )
1#
1&
#480
0#
0&
#485
b10 )
1#
1&
#490
0#
0&
#495
b11 )
1#
1&
#500
0#
0&
#505
b100 )
1#
1&
#510
0#
0&
#515
b101 )
1#
1&
#520
0#
0&
#525
b110 )
1#
1&
#530
0#
0&
1%
1(
#535
1+
b111 )
1#
1&
#540
0#
0&
#545
b1000 )
1#
1&
#550
0#
0&
#555
b1001 )
1#
1&
#560
0#
0&
#565
b1010 )
1#
1&
#570
0#
0&
#575
b1011 )
1#
1&
#580
0#
0&
#585
b1100 )
1#
1&
#590
0#
0&
#595
b1101 )
1#
1&
#600
0#
0&
#605
b1110 )
1#
1&
#610
0#
0&
#615
b1111 )
1#
1&
#620
0#
0&
#625
b10 *
b10 ,
b10 !
b0 )
1#
1&
#630
0#
0&
#635
b1 )
1#
1&
#640
0#
0&
#645
b10 )
1#
1&
#650
0#
0&
#655
b11 )
1#
1&
#660
0#
0&
#665
b100 )
1#
1&
#670
0#
0&
#675
b101 )
1#
1&
#680
0#
0&
#685
b110 )
1#
1&
#690
0#
0&
#695
b111 )
1#
1&
#700
0#
0&
#705
b1000 )
1#
1&
#710
0#
0&
#715
b1001 )
1#
1&
#720
0#
0&
#725
b1010 )
1#
1&
#730
0#
0&
#735
b1011 )
1#
1&
#740
0#
0&
#745
b1100 )
1#
1&
#750
0#
0&
#755
b1101 )
1#
1&
#760
0#
0&
#765
b1110 )
1#
1&
#770
0#
0&
#775
b1111 )
1#
1&
#780
0#
0&
#785
b11 *
b110 ,
b110 !
b0 )
1#
1&
#790
0#
0&
#795
b1 )
1#
1&
#800
0#
0&
#805
b10 )
1#
1&
#810
0#
0&
#815
b11 )
1#
1&
#820
0#
0&
#825
b100 )
1#
1&
#830
0#
0&
#835
b101 )
1#
1&
#840
0#
0&
#845
b110 )
1#
1&
#850
0#
0&
0%
0(
#855
0+
b111 )
1#
1&
#860
0#
0&
#865
b1000 )
1#
1&
#870
0#
0&
#875
b1001 )
1#
1&
#880
0#
0&
#885
b1010 )
1#
1&
#890
0#
0&
#895
b1011 )
1#
1&
#900
0#
0&
#905
b1100 )
1#
1&
#910
0#
0&
#915
b1101 )
1#
1&
#920
0#
0&
#925
b1110 )
1#
1&
#930
0#
0&
#935
b1111 )
1#
1&
#940
0#
0&
#945
b100 *
b110 ,
b0 )
1#
1&
#950
0#
0&
#955
b1 )
1#
1&
#960
0#
0&
#965
b10 )
1#
1&
#970
0#
0&
#975
b11 )
1#
1&
#980
0#
0&
#985
b100 )
1#
1&
#990
0#
0&
#995
b101 )
1#
1&
#1000
0#
0&
#1005
b110 )
1#
1&
#1010
0#
0&
1%
1(
#1015
1+
b111 )
1#
1&
#1020
0#
0&
#1025
b1000 )
1#
1&
#1030
0#
0&
#1035
b1001 )
1#
1&
#1040
0#
0&
#1045
b1010 )
1#
1&
#1050
0#
0&
#1055
b1011 )
1#
1&
#1060
0#
0&
#1065
b1100 )
1#
1&
#1070
0#
0&
#1075
b1101 )
1#
1&
#1080
0#
0&
#1085
b1110 )
1#
1&
#1090
0#
0&
#1095
b1111 )
1#
1&
#1100
0#
0&
#1105
b101 *
b10110 ,
b10110 !
b0 )
1#
1&
#1110
0#
0&
#1115
b1 )
1#
1&
#1120
0#
0&
#1125
b10 )
1#
1&
#1130
0#
0&
#1135
b11 )
1#
1&
#1140
0#
0&
#1145
b100 )
1#
1&
#1150
0#
0&
#1155
b101 )
1#
1&
#1160
0#
0&
#1165
b110 )
1#
1&
#1170
0#
0&
#1175
b111 )
1#
1&
#1180
0#
0&
#1185
b1000 )
1#
1&
#1190
0#
0&
#1195
b1001 )
1#
1&
#1200
0#
0&
#1205
b1010 )
1#
1&
#1210
0#
0&
#1215
b1011 )
1#
1&
#1220
0#
0&
#1225
b1100 )
1#
1&
#1230
0#
0&
#1235
b1101 )
1#
1&
#1240
0#
0&
#1245
b1110 )
1#
1&
#1250
0#
0&
#1255
b1111 )
1#
1&
#1260
0#
0&
#1265
b110 *
b110110 ,
b110110 !
b0 )
1#
1&
#1270
0#
0&
#1275
b1 )
1#
1&
#1280
0#
0&
#1285
b10 )
1#
1&
#1290
0#
0&
#1295
b11 )
1#
1&
#1300
0#
0&
#1305
b100 )
1#
1&
#1310
0#
0&
#1315
b101 )
1#
1&
#1320
0#
0&
#1325
b110 )
1#
1&
#1330
0#
0&
0%
0(
#1335
0+
b111 )
1#
1&
#1340
0#
0&
#1345
b1000 )
1#
1&
#1350
0#
0&
#1355
b1001 )
1#
1&
#1360
0#
0&
#1365
b1010 )
1#
1&
#1370
0#
0&
#1375
b1011 )
1#
1&
#1380
0#
0&
#1385
b1100 )
1#
1&
#1390
0#
0&
#1395
b1101 )
1#
1&
#1400
0#
0&
#1405
b1110 )
1#
1&
#1410
0#
0&
#1415
b1111 )
1#
1&
#1420
0#
0&
#1425
b111 *
b110110 ,
b0 )
1#
1&
#1430
0#
0&
#1435
b1 )
1#
1&
#1440
0#
0&
#1445
b10 )
1#
1&
#1450
0#
0&
#1455
b11 )
1#
1&
#1460
0#
0&
#1465
b100 )
1#
1&
#1470
0#
0&
#1475
b101 )
1#
1&
#1480
0#
0&
#1485
b110 )
1#
1&
#1490
0#
0&
1%
1(
#1495
1+
b111 )
1#
1&
#1500
0#
0&
#1505
b1000 )
1#
1&
#1510
0#
0&
#1515
b1001 )
1#
1&
#1520
0#
0&
#1525
b1010 )
1#
1&
#1530
0#
0&
#1535
b1011 )
1#
1&
#1540
0#
0&
#1545
b1100 )
1#
1&
#1550
0#
0&
#1555
b1101 )
1#
1&
#1560
0#
0&
#1565
b1110 )
1#
1&
#1570
0#
0&
#1575
b1111 )
1#
1&
#1580
0#
0&
#1585
b11 .
b10110110 ,
b10110110 !
b0 )
1#
1&
#1590
0#
0&
#1595
b1 )
1-
1"
1#
1&
#1600
0#
0&
#1605
b10 )
1#
1&
#1610
0#
0&
#1615
b11 )
1#
1&
#1620
0#
0&
#1625
b100 )
1#
1&
#1630
0#
0&
#1635
b101 )
1#
1&
#1640
0#
0&
#1645
b110 )
1#
1&
#1650
0#
0&
#1655
b111 )
1#
1&
#1660
0#
0&
#1665
b1000 )
1#
1&
#1670
0#
0&
#1675
b1001 )
1#
1&
#1680
0#
0&
#1685
b1010 )
1#
1&
#1690
0#
0&
#1695
b1011 )
1#
1&
#1700
0#
0&
#1705
b1100 )
1#
1&
#1710
0#
0&
#1715
b1101 )
1#
1&
#1720
0#
0&
#1725
b1110 )
1#
1&
#1730
0#
0&
#1735
b1111 )
1#
1&
#1740
0#
0&
#1745
b0 .
b0 )
1#
1&
#1750
0#
0&
#1755
0-
0"
1#
1&
#1760
0#
0&
#1765
1#
1&
#1770
0#
0&
#1775
1#
1&
#1780
0#
0&
#1785
1#
1&
#1790
0#
0&
#1795
1#
1&
#1800
0#
0&
#1805
1#
1&
#1810
0#
0&
0%
0(
#1815
b0 ,
b0 !
b1 .
0+
1#
1&
#1820
0#
0&
#1825
b1 )
1#
1&
#1830
0#
0&
#1835
b10 )
1#
1&
#1840
0#
0&
#1845
b11 )
1#
1&
#1850
0#
0&
#1855
b100 )
1#
1&
#1860
0#
0&
#1865
b101 )
1#
1&
#1870
0#
0&
#1875
b110 )
1#
1&
#1880
0#
0&
#1885
b111 )
1#
1&
#1890
0#
0&
#1895
b1000 )
1#
1&
#1900
0#
0&
#1905
b10 .
b0 *
b0 )
1#
1&
#1910
0#
0&
#1915
b1 )
1#
1&
#1920
0#
0&
#1925
b10 )
1#
1&
#1930
0#
0&
#1935
b11 )
1#
1&
#1940
0#
0&
#1945
b100 )
1#
1&
#1950
0#
0&
#1955
b101 )
1#
1&
#1960
0#
0&
#1965
b110 )
1#
1&
#1970
0#
0&
1%
1(
#1975
1+
b111 )
1#
1&
#1980
0#
0&
#1985
b1000 )
1#
1&
#1990
0#
0&
#1995
b1001 )
1#
1&
#2000
0#
0&
#2005
b1010 )
1#
1&
#2010
0#
0&
#2015
b1011 )
1#
1&
#2020
0#
0&
#2025
b1100 )
1#
1&
#2030
0#
0&
#2035
b1101 )
1#
1&
#2040
0#
0&
#2045
b1110 )
1#
1&
#2050
0#
0&
#2055
b1111 )
1#
1&
#2060
0#
0&
#2065
b1 *
b1 ,
b1 !
b0 )
1#
1&
#2070
0#
0&
#2075
b1 )
1#
1&
#2080
0#
0&
#2085
b10 )
1#
1&
#2090
0#
0&
#2095
b11 )
1#
1&
#2100
0#
0&
#2105
b100 )
1#
1&
#2110
0#
0&
#2115
b101 )
1#
1&
#2120
0#
0&
#2125
b110 )
1#
1&
#2130
0#
0&
#2135
b111 )
1#
1&
#2140
0#
0&
#2145
b1000 )
1#
1&
#2150
0#
0&
#2155
b1001 )
1#
1&
#2160
0#
0&
#2165
b1010 )
1#
1&
#2170
0#
0&
#2175
b1011 )
1#
1&
#2180
0#
0&
#2185
b1100 )
1#
1&
#2190
0#
0&
#2195
b1101 )
1#
1&
#2200
0#
0&
#2205
b1110 )
1#
1&
#2210
0#
0&
#2215
b1111 )
1#
1&
#2220
0#
0&
#2225
b10 *
b11 ,
b11 !
b0 )
1#
1&
#2230
0#
0&
#2235
b1 )
1#
1&
#2240
0#
0&
#2245
b10 )
1#
1&
#2250
0#
0&
#2255
b11 )
1#
1&
#2260
0#
0&
#2265
b100 )
1#
1&
#2270
0#
0&
#2275
b101 )
1#
1&
#2280
0#
0&
#2285
b110 )
1#
1&
#2290
0#
0&
#2295
b111 )
1#
1&
#2300
0#
0&
#2305
b1000 )
1#
1&
#2310
0#
0&
#2315
b1001 )
1#
1&
#2320
0#
0&
#2325
b1010 )
1#
1&
#2330
0#
0&
#2335
b1011 )
1#
1&
#2340
0#
0&
#2345
b1100 )
1#
1&
#2350
0#
0&
#2355
b1101 )
1#
1&
#2360
0#
0&
#2365
b1110 )
1#
1&
#2370
0#
0&
#2375
b1111 )
1#
1&
#2380
0#
0&
#2385
b11 *
b111 ,
b111 !
b0 )
1#
1&
#2390
0#
0&
#2395
b1 )
1#
1&
#2400
0#
0&
#2405
b10 )
1#
1&
#2410
0#
0&
#2415
b11 )
1#
1&
#2420
0#
0&
#2425
b100 )
1#
1&
#2430
0#
0&
#2435
b101 )
1#
1&
#2440
0#
0&
#2445
b110 )
1#
1&
#2450
0#
0&
#2455
b111 )
1#
1&
#2460
0#
0&
#2465
b1000 )
1#
1&
#2470
0#
0&
#2475
b1001 )
1#
1&
#2480
0#
0&
#2485
b1010 )
1#
1&
#2490
0#
0&
#2495
b1011 )
1#
1&
#2500
0#
0&
#2505
b1100 )
1#
1&
#2510
0#
0&
#2515
b1101 )
1#
1&
#2520
0#
0&
#2525
b1110 )
1#
1&
#2530
0#
0&
#2535
b1111 )
1#
1&
#2540
0#
0&
#2545
b100 *
b1111 ,
b1111 !
b0 )
1#
1&
#2550
0#
0&
#2555
b1 )
1#
1&
#2560
0#
0&
#2565
b10 )
1#
1&
#2570
0#
0&
#2575
b11 )
1#
1&
#2580
0#
0&
#2585
b100 )
1#
1&
#2590
0#
0&
#2595
b101 )
1#
1&
#2600
0#
0&
#2605
b110 )
1#
1&
#2610
0#
0&
#2615
b111 )
1#
1&
#2620
0#
0&
#2625
b1000 )
1#
1&
#2630
0#
0&
#2635
b1001 )
1#
1&
#2640
0#
0&
#2645
b1010 )
1#
1&
#2650
0#
0&
#2655
b1011 )
1#
1&
#2660
0#
0&
#2665
b1100 )
1#
1&
#2670
0#
0&
#2675
b1101 )
1#
1&
#2680
0#
0&
#2685
b1110 )
1#
1&
#2690
0#
0&
#2695
b1111 )
1#
1&
#2700
0#
0&
#2705
b101 *
b11111 ,
b11111 !
b0 )
1#
1&
#2710
0#
0&
#2715
b1 )
1#
1&
#2720
0#
0&
#2725
b10 )
1#
1&
#2730
0#
0&
#2735
b11 )
1#
1&
#2740
0#
0&
#2745
b100 )
1#
1&
#2750
0#
0&
#2755
b101 )
1#
1&
#2760
0#
0&
#2765
b110 )
1#
1&
#2770
0#
0&
#2775
b111 )
1#
1&
#2780
0#
0&
#2785
b1000 )
1#
1&
#2790
0#
0&
#2795
b1001 )
1#
1&
#2800
0#
0&
#2805
b1010 )
1#
1&
#2810
0#
0&
#2815
b1011 )
1#
1&
#2820
0#
0&
#2825
b1100 )
1#
1&
#2830
0#
0&
#2835
b1101 )
1#
1&
#2840
0#
0&
#2845
b1110 )
1#
1&
#2850
0#
0&
#2855
b1111 )
1#
1&
#2860
0#
0&
#2865
b110 *
b111111 ,
b111111 !
b0 )
1#
1&
#2870
0#
0&
#2875
b1 )
1#
1&
#2880
0#
0&
#2885
b10 )
1#
1&
#2890
0#
0&
#2895
b11 )
1#
1&
#2900
0#
0&
#2905
b100 )
1#
1&
#2910
0#
0&
#2915
b101 )
1#
1&
#2920
0#
0&
#2925
b110 )
1#
1&
#2930
0#
0&
#2935
b111 )
1#
1&
#2940
0#
0&
#2945
b1000 )
1#
1&
#2950
0#
0&
#2955
b1001 )
1#
1&
#2960
0#
0&
#2965
b1010 )
1#
1&
#2970
0#
0&
#2975
b1011 )
1#
1&
#2980
0#
0&
#2985
b1100 )
1#
1&
#2990
0#
0&
#2995
b1101 )
1#
1&
#3000
0#
0&
#3005
b1110 )
1#
1&
#3010
0#
0&
#3015
b1111 )
1#
1&
#3020
0#
0&
#3025
b111 *
b1111111 ,
b1111111 !
b0 )
1#
1&
#3030
0#
0&
#3035
b1 )
1#
1&
#3040
0#
0&
#3045
b10 )
1#
1&
#3050
0#
0&
#3055
b11 )
1#
1&
#3060
0#
0&
#3065
b100 )
1#
1&
#3070
0#
0&
#3075
b101 )
1#
1&
#3080
0#
0&
#3085
b110 )
1#
1&
#3090
0#
0&
#3095
b111 )
1#
1&
#3100
0#
0&
#3105
b1000 )
1#
1&
#3110
0#
0&
#3115
b1001 )
1#
1&
#3120
0#
0&
#3125
b1010 )
1#
1&
#3130
0#
0&
#3135
b1011 )
1#
1&
#3140
0#
0&
#3145
b1100 )
1#
1&
#3150
0#
0&
#3155
b1101 )
1#
1&
#3160
0#
0&
#3165
b1110 )
1#
1&
#3170
0#
0&
#3175
b1111 )
1#
1&
#3180
0#
0&
#3185
b11 .
b11111111 ,
b11111111 !
b0 )
1#
1&
#3190
0#
0&
#3195
b1 )
1-
1"
1#
1&
#3200
0#
0&
#3205
b10 )
1#
1&
#3210
0#
0&
#3215
b11 )
1#
1&
#3220
0#
0&
#3225
b100 )
1#
1&
#3230
0#
0&
#3235
b101 )
1#
1&
#3240
0#
0&
#3245
b110 )
1#
1&
#3250
0#
0&
#3255
b111 )
1#
1&
#3260
0#
0&
#3265
b1000 )
1#
1&
#3270
0#
0&
#3275
b1001 )
1#
1&
#3280
0#
0&
#3285
b1010 )
1#
1&
#3290
0#
0&
#3295
b1011 )
1#
1&
#3300
0#
0&
#3305
b1100 )
1#
1&
#3310
0#
0&
#3315
b1101 )
1#
1&
#3320
0#
0&
#3325
b1110 )
1#
1&
#3330
0#
0&
#3335
b1111 )
1#
1&
#3340
0#
0&
#3345
b0 .
b0 )
1#
1&
#3350
0#
0&
#3355
0-
0"
1#
1&
#3360
0#
0&
#3365
1#
1&
#3370
0#
0&
#3375
1#
1&
#3380
0#
0&
#3385
1#
1&
#3390
0#
0&
#3395
1#
1&
#3400
0#
0&
#3405
1#
1&
#3410
0#
0&
0%
0(
#3415
b0 ,
b0 !
b1 .
0+
1#
1&
#3420
0#
0&
#3425
b1 )
1#
1&
#3430
0#
0&
#3435
b10 )
1#
1&
#3440
0#
0&
#3445
b11 )
1#
1&
#3450
0#
0&
#3455
b100 )
1#
1&
#3460
0#
0&
#3465
b101 )
1#
1&
#3470
0#
0&
#3475
b110 )
1#
1&
#3480
0#
0&
#3485
b111 )
1#
1&
#3490
0#
0&
#3495
b1000 )
1#
1&
#3500
0#
0&
#3505
b10 .
b0 *
b0 )
1#
1&
#3510
0#
0&
#3515
b1 )
1#
1&
#3520
0#
0&
#3525
b10 )
1#
1&
#3530
0#
0&
#3535
b11 )
1#
1&
#3540
0#
0&
#3545
b100 )
1#
1&
#3550
0#
0&
#3555
b101 )
1#
1&
#3560
0#
0&
#3565
b110 )
1#
1&
#3570
0#
0&
1%
1(
#3575
1+
b111 )
1#
1&
#3580
0#
0&
#3585
b1000 )
1#
1&
#3590
0#
0&
#3595
b1001 )
1#
1&
#3600
0#
0&
#3605
b1010 )
1#
1&
#3610
0#
0&
#3615
b1011 )
1#
1&
#3620
0#
0&
#3625
b1100 )
1#
1&
#3630
0#
0&
#3635
b1101 )
1#
1&
#3640
0#
0&
#3645
b1110 )
1#
1&
#3650
0#
0&
#3655
b1111 )
1#
1&
#3660
0#
0&
#3665
b1 *
b1 ,
b1 !
b0 )
1#
1&
#3670
0#
0&
#3675
b1 )
1#
1&
#3680
0#
0&
#3685
b10 )
1#
1&
#3690
0#
0&
#3695
b11 )
1#
1&
#3700
0#
0&
#3705
b100 )
1#
1&
#3710
0#
0&
#3715
b101 )
1#
1&
#3720
0#
0&
#3725
b110 )
1#
1&
#3730
0#
0&
0%
0(
#3735
0+
b111 )
1#
1&
#3740
0#
0&
#3745
b1000 )
1#
1&
#3750
0#
0&
#3755
b1001 )
1#
1&
#3760
0#
0&
#3765
b1010 )
1#
1&
#3770
0#
0&
#3775
b1011 )
1#
1&
#3780
0#
0&
#3785
b1100 )
1#
1&
#3790
0#
0&
#3795
b1101 )
1#
1&
#3800
0#
0&
#3805
b1110 )
1#
1&
#3810
0#
0&
#3815
b1111 )
1#
1&
#3820
0#
0&
#3825
b10 *
b1 ,
b0 )
1#
1&
#3830
0#
0&
#3835
b1 )
1#
1&
#3840
0#
0&
#3845
b10 )
1#
1&
#3850
0#
0&
#3855
b11 )
1#
1&
#3860
0#
0&
#3865
b100 )
1#
1&
#3870
0#
0&
#3875
b101 )
1#
1&
#3880
0#
0&
#3885
b110 )
1#
1&
#3890
0#
0&
1%
1(
#3895
1+
b111 )
1#
1&
#3900
0#
0&
#3905
b1000 )
1#
1&
#3910
0#
0&
#3915
b1001 )
1#
1&
#3920
0#
0&
#3925
b1010 )
1#
1&
#3930
0#
0&
#3935
b1011 )
1#
1&
#3940
0#
0&
#3945
b1100 )
1#
1&
#3950
0#
0&
#3955
b1101 )
1#
1&
#3960
0#
0&
#3965
b1110 )
1#
1&
#3970
0#
0&
#3975
b1111 )
1#
1&
#3980
0#
0&
#3985
b11 *
b101 ,
b101 !
b0 )
1#
1&
#3990
0#
0&
#3995
b1 )
1#
1&
#4000
0#
0&
#4005
b10 )
1#
1&
#4010
0#
0&
#4015
b11 )
1#
1&
#4020
0#
0&
#4025
b100 )
1#
1&
#4030
0#
0&
#4035
b101 )
1#
1&
#4040
0#
0&
#4045
b110 )
1#
1&
#4050
0#
0&
#4055
b111 )
1#
1&
#4060
0#
0&
#4065
b1000 )
1#
1&
#4070
0#
0&
#4075
b1001 )
1#
1&
#4080
0#
0&
#4085
b1010 )
1#
1&
#4090
0#
0&
#4095
b1011 )
1#
1&
#4100
0#
0&
#4105
b1100 )
1#
1&
#4110
0#
0&
#4115
b1101 )
1#
1&
#4120
0#
0&
#4125
b1110 )
1#
1&
#4130
0#
0&
#4135
b1111 )
1#
1&
#4140
0#
0&
#4145
b100 *
b1101 ,
b1101 !
b0 )
1#
1&
#4150
0#
0&
#4155
b1 )
1#
1&
#4160
0#
0&
#4165
b10 )
1#
1&
#4170
0#
0&
#4175
b11 )
1#
1&
#4180
0#
0&
#4185
b100 )
1#
1&
#4190
0#
0&
#4195
b101 )
1#
1&
#4200
0#
0&
#4205
b110 )
1#
1&
#4210
0#
0&
0%
0(
#4215
0+
b111 )
1#
1&
#4220
0#
0&
#4225
b1000 )
1#
1&
#4230
0#
0&
#4235
b1001 )
1#
1&
#4240
0#
0&
#4245
b1010 )
1#
1&
#4250
0#
0&
#4255
b1011 )
1#
1&
#4260
0#
0&
#4265
b1100 )
1#
1&
#4270
0#
0&
#4275
b1101 )
1#
1&
#4280
0#
0&
#4285
b1110 )
1#
1&
#4290
0#
0&
#4295
b1111 )
1#
1&
#4300
0#
0&
#4305
b101 *
b1101 ,
b0 )
1#
1&
#4310
0#
0&
#4315
b1 )
1#
1&
#4320
0#
0&
#4325
b10 )
1#
1&
#4330
0#
0&
#4335
b11 )
1#
1&
#4340
0#
0&
#4345
b100 )
1#
1&
#4350
0#
0&
#4355
b101 )
1#
1&
#4360
0#
0&
#4365
b110 )
1#
1&
#4370
0#
0&
#4375
b111 )
1#
1&
#4380
0#
0&
#4385
b1000 )
1#
1&
#4390
0#
0&
#4395
b1001 )
1#
1&
#4400
0#
0&
#4405
b1010 )
1#
1&
#4410
0#
0&
#4415
b1011 )
1#
1&
#4420
0#
0&
#4425
b1100 )
1#
1&
#4430
0#
0&
#4435
b1101 )
1#
1&
#4440
0#
0&
#4445
b1110 )
1#
1&
#4450
0#
0&
#4455
b1111 )
1#
1&
#4460
0#
0&
#4465
b110 *
b1101 ,
b0 )
1#
1&
#4470
0#
0&
#4475
b1 )
1#
1&
#4480
0#
0&
#4485
b10 )
1#
1&
#4490
0#
0&
#4495
b11 )
1#
1&
#4500
0#
0&
#4505
b100 )
1#
1&
#4510
0#
0&
#4515
b101 )
1#
1&
#4520
0#
0&
#4525
b110 )
1#
1&
#4530
0#
0&
1%
1(
#4535
1+
b111 )
1#
1&
#4540
0#
0&
#4545
b1000 )
1#
1&
#4550
0#
0&
#4555
b1001 )
1#
1&
#4560
0#
0&
#4565
b1010 )
1#
1&
#4570
0#
0&
#4575
b1011 )
1#
1&
#4580
0#
0&
#4585
b1100 )
1#
1&
#4590
0#
0&
#4595
b1101 )
1#
1&
#4600
0#
0&
#4605
b1110 )
1#
1&
#4610
0#
0&
#4615
b1111 )
1#
1&
#4620
0#
0&
#4625
b111 *
b1001101 ,
b1001101 !
b0 )
1#
1&
#4630
0#
0&
#4635
b1 )
1#
1&
#4640
0#
0&
#4645
b10 )
1#
1&
#4650
0#
0&
#4655
b11 )
1#
1&
#4660
0#
0&
#4665
b100 )
1#
1&
#4670
0#
0&
#4675
b101 )
1#
1&
#4680
0#
0&
#4685
b110 )
1#
1&
#4690
0#
0&
0%
0(
#4695
0+
b111 )
1#
1&
#4700
0#
0&
#4705
b1000 )
1#
1&
#4710
0#
0&
#4715
b1001 )
1#
1&
#4720
0#
0&
#4725
b1010 )
1#
1&
#4730
0#
0&
#4735
b1011 )
1#
1&
#4740
0#
0&
#4745
b1100 )
1#
1&
#4750
0#
0&
#4755
b1101 )
1#
1&
#4760
0#
0&
#4765
b1110 )
1#
1&
#4770
0#
0&
#4775
b1111 )
1#
1&
#4780
0#
0&
#4785
b11 .
b1001101 ,
b0 )
1#
1&
#4790
0#
0&
#4795
b1 )
1-
1"
1#
1&
#4800
0#
0&
#4805
b10 )
1#
1&
#4810
0#
0&
#4815
b11 )
1#
1&
#4820
0#
0&
#4825
b100 )
1#
1&
#4830
0#
0&
#4835
b101 )
1#
1&
#4840
0#
0&
#4845
b110 )
1#
1&
