LEVEL - 2 FSMs Verilog HDL Problems/1. Sequence Detector (Mealy)/sequence_detector.v
module sequence_detector(data_out,data_in,clk,reset);

    output reg data_out;

    input data_in;
    input clk,reset;

    reg [1:0] state,next_state;

    parameter S0=2'b00 , S1=2'b01 , S2=2'b10 , S3=2'b11;

    always @ (posedge clk) begin

        if (reset) state <= S0;

        else state <= next_state;

    end

    always @ (*) begin

        case(state)

        S0: begin 
            if (data_in == 1) next_state = S1;
            else next_state = S0;
            data_out = 1'b0;
        end

        S1: begin
            if(data_in == 0) next_state = S2;
            else next_state = S1;
            data_out = 1'b0;
        end

        S2: begin
            if(data_in == 1) next_state = S3;
            else next_state = S0;
            data_out  = 1'b0;
        end

        S3: begin
            if(data_in == 1) begin
                next_state = S1;
                data_out = 1'b1;
            end
            else next_state = S2;
        end

        endcase

    end

endmodule

LEVEL - 2 FSMs Verilog HDL Problems/1. Sequence Detector/sequencedetector_tb.v
module sequence_detector_tb();

    wire data_out;

    reg data_in,clk,reset;

    sequence_detector uut(data_out,data_in,clk,reset);

    initial clk = 0;

    always #5 clk = ~clk;

    always @ (posedge clk) begin

        #3;
        $display("t = %0t , RESET = %b , INPUT = %b , OUTPUT = %b ",$time,reset,data_in,data_out);

    end

    initial begin 

        $dumpfile("sequence_detector.vcd");
        $dumpvars(0,sequence_detector_tb);

        data_in=1'b0;reset=1;#20;
        reset=0;#20;

        @(posedge clk);#2;data_in=1'b1;
        @(posedge clk);#2;data_in=1'b0;
        @(posedge clk);#2;data_in=1'b1;
        @(posedge clk);#2;data_in=1'b1;
        @(posedge clk);#2;data_in=1'b0;
        @(posedge clk);#2;data_in=1'b1;
        @(posedge clk);#2;data_in=1'b1;
        @(posedge clk);#10;

        $finish;

    end

endmodule

LEVEL - 2 FSMs Verilog HDL Problems/1. Sequence Detector (Mealy)/sequence_detector.vcd
$date
	Sat Jul 04 19:56:46 2026
$end
$version
	Icarus Verilog
$end
$timescale
	1s
$end
$scope module sequence_detector_tb $end
$var wire 1 ! data_out $end
$var reg 1 " clk $end
$var reg 1 # data_in $end
$var reg 1 $ reset $end
$scope module uut $end
$var wire 1 % clk $end
$var wire 1 & data_in $end
$var wire 1 ' reset $end
$var reg 1 ( data_out $end
$var reg 2 ) next_state [1:0] $end
$var reg 2 * state [1:0] $end
$upscope $end
$upscope $end
$enddefinitions $end
#0
$dumpvars
bx *
bx )
x(
1'
0&
0%
1$
0#
0"
x!
$end
#5
0(
0!
b0 )
b0 *
1"
1%
#10
0"
0%
#15
1"
1%
#20
0"
0%
0$
0'
#25
1"
1%
#30
0"
0%
#35
1"
1%
#40
0"
0%
#45
1"
1%
#47
b1 )
1#
1&
#50
0"
0%
#55
b1 *
1"
1%
#57
b10 )
0#
0&
#60
0"
0%
#65
b0 )
b10 *
1"
1%
#67
b11 )
1#
1&
#70
0"
0%
#75
1(
1!
b1 )
b11 *
1"
1%
#80
0"
0%
#85
0(
0!
b1 *
1"
1%
#87
b10 )
0#
0&
#90
0"
0%
#95
b0 )
b10 *
1"
1%
#97
b11 )
1#
1&
#100
0"
0%
#105
1(
1!
b1 )
b11 *
1"
1%
#110
0"
0%
#115
0(
0!
b1 *
1"
1%
