LEVEL - 2 Arithmetic Verilog HDL Problems/2. 16-bit Carry Look Ahead Adder/4bitcarrylookaheadadder.v
module carrylookaheadadder_4bit(Sum_out,C_out,A,B,C_in);

    output [3:0] Sum_out;
    output C_out;
    input [3:0] A,B;
    input C_in;

    wire [3:0] P,G,C;

    assign P = A ^ B;
    assign G = A & B;

    assign C[0] = C_in;
    assign C[1] = G[0] | (P[0] & C_in);
    assign C[2] = G[1] | (P[1] & G[0]) | (P[1] & P[0] & C_in);
    assign C[3] = G[2] | (P[2] & G[1]) | (P[2] & P[1] & G[0]) | (P[2] & P[1] & P[0] & C_in);
    assign C_out = G[3] | (P[3] & G[2]) | (P[3] & P[2] & G[1]) | (P[3] & P[2] & P[1] & G[0]) | (P[3] & P[2] & P[1] & P[0] & C_in);

    assign Sum_out = P^C;

endmodule

LEVEL - 2 Arithmetic Verilog HDL Problems/2. 16-bit Carry Look Ahead Adder/16bitcarrylookaheadadder.v
module carrylookaheadadder_16bit(SUM,C_out,A,B,C_in);

    output [15:0] SUM;
    output C_out;
    input [15:0] A,B;
    input C_in;
    wire [3:0]C;

    assign C[0] = C_in;

    carrylookaheadadder_4bit CLA_3to0(.Sum_out(SUM[3:0]),.C_out(C[1]),.A(A[3:0]),.B(B[3:0]),.C_in(C[0]));
    carrylookaheadadder_4bit CLA_7to4(.Sum_out(SUM[7:4]),.C_out(C[2]),.A(A[7:4]),.B(B[7:4]),.C_in(C[1]));
    carrylookaheadadder_4bit CLA_11to8(.Sum_out(SUM[11:8]),.C_out(C[3]),.A(A[11:8]),.B(B[11:8]),.C_in(C[2]));
    carrylookaheadadder_4bit CLA_15to12(.Sum_out(SUM[15:12]),.C_out(C_out),.A(A[15:12]),.B(B[15:12]),.C_in(C[3]));

endmodule

LEVEL - 2 Arithmetic Verilog HDL Problems/2. 16-bit Carry Look Ahead Adder/16bitlookaheadadder_tb.v
module carrylookaheadadder_16bit_tb();

    reg [15:0] A,B;
    reg C_in;
    wire [15:0] SUM;
    wire C_out;

    carrylookaheadadder_16bit uut(.SUM(SUM),.C_out(C_out),.A(A),.B(B),.C_in(C_in));

    always  @ (A,B,C_in,SUM,C_out) begin
        
        #1;
        $display("A = %h , B = %h , C_in = %b || SUM = %h , CARRY_OUT = %b ",A,B,C_in,SUM,C_out);

    end

    initial begin 

        $dumpfile("16-bitcarrylookheadadder.vcd");
        $dumpvars(0,carrylookaheadadder_16bit_tb);

        A = 16'h0000; B = 16'h0000; C_in = 0; #10;
        A = 16'h0001; B = 16'h0001; C_in = 0; #10;
        A = 16'h000F; B = 16'h0001; C_in = 0; #10;
        A = 16'h00FF; B = 16'h0001; C_in = 0; #10;
        A = 16'h0FFF; B = 16'h0001; C_in = 0; #10;
        A = 16'hFFFF; B = 16'h0001; C_in = 0; #10;
        A = 16'hFFFF; B = 16'hFFFF; C_in = 0; #10;
        A = 16'h1234; B = 16'h4321; C_in = 0; #10;
        A = 16'hAAAA; B = 16'h5555; C_in = 0; #10;

        $finish;

    end

endmodule

LEVEL - 2 Arithmetic Verilog HDL Problems/2. 16-bit Carry Look Ahead Adder/16-bitcarrylookheadadder.vcd
$date
	Mon Jun 29 21:18:36 2026
$end
$version
	Icarus Verilog
$end
$timescale
	1s
$end
$scope module carrylookaheadadder_16bit_tb $end
$var wire 1 ! C_out $end
$var wire 16 " SUM [15:0] $end
$var reg 16 # A [15:0] $end
$var reg 16 $ B [15:0] $end
$var reg 1 % C_in $end
$scope module uut $end
$var wire 16 & A [15:0] $end
$var wire 16 ' B [15:0] $end
$var wire 4 ( C [3:0] $end
$var wire 1 ) C_in $end
$var wire 1 ! C_out $end
$var wire 16 * SUM [15:0] $end
$scope module CLA_3to0 $end
$var wire 4 + A [3:0] $end
$var wire 4 , B [3:0] $end
$var wire 4 - C [3:0] $end
$var wire 1 . C_in $end
$var wire 1 / C_out $end
$var wire 4 0 G [3:0] $end
$var wire 4 1 P [3:0] $end
$var wire 4 2 Sum_out [3:0] $end
$upscope $end
$scope module CLA_7to4 $end
$var wire 4 3 A [3:0] $end
$var wire 4 4 B [3:0] $end
$var wire 4 5 C [3:0] $end
$var wire 1 6 C_in $end
$var wire 1 7 C_out $end
$var wire 4 8 G [3:0] $end
$var wire 4 9 P [3:0] $end
$var wire 4 : Sum_out [3:0] $end
$upscope $end
$scope module CLA_11to8 $end
$var wire 4 ; A [3:0] $end
$var wire 4 < B [3:0] $end
$var wire 4 = C [3:0] $end
$var wire 1 > C_in $end
$var wire 1 ? C_out $end
$var wire 4 @ G [3:0] $end
$var wire 4 A P [3:0] $end
$var wire 4 B Sum_out [3:0] $end
$upscope $end
$scope module CLA_15to12 $end
$var wire 4 C A [3:0] $end
$var wire 4 D B [3:0] $end
$var wire 4 E C [3:0] $end
$var wire 1 F C_in $end
$var wire 1 ! C_out $end
$var wire 4 G G [3:0] $end
$var wire 4 H P [3:0] $end
$var wire 4 I Sum_out [3:0] $end
$upscope $end
$upscope $end
$upscope $end
$enddefinitions $end
#0
$dumpvars
b0 I
b0 H
b0 G
0F
b0 E
b0 D
b0 C
b0 B
b0 A
b0 @
0?
0>
b0 =
b0 <
b0 ;
b0 :
b0 9
b0 8
07
06
b0 5
b0 4
b0 3
b0 2
b0 1
b0 0
0/
0.
b0 -
b0 ,
b0 +
b0 *
0)
b0 (
b0 '
b0 &
0%
b0 $
b0 #
b0 "
0!
$end
#10
b10 2
b10 "
b10 *
b10 -
b1 0
b1 ,
b1 +
b1 $
b1 '
b1 #
b1 &
#20
b1 :
b1 5
16
1/
b10 (
b1110 -
b0 2
b10000 "
b10000 *
b1110 1
b1111 +
b1111 #
b1111 &
#30
b1 B
b1 =
1>
17
b110 (
b1111 5
b0 :
b100000000 "
b100000000 *
b1111 9
b1111 3
b11111111 #
b11111111 &
#40
b1 I
b1 E
1F
1?
b1110 (
b1111 =
b0 B
b1000000000000 "
b1000000000000 *
b1111 A
b1111 ;
b111111111111 #
b111111111111 &
#50
1!
b1111 E
b0 I
b0 "
b0 *
b1111 H
b1111 C
b1111111111111111 #
b1111111111111111 &
#60
b1110 2
b1111 :
b1111 B
b1111 I
b1111111111111110 "
b1111111111111110 *
b0 1
b1111 0
b0 9
b1111 8
b0 A
b1111 @
b0 H
b1111 G
b1111 ,
b1111 4
b1111 <
b1111 D
b1111111111111111 $
b1111111111111111 '
#70
06
0>
0F
0/
07
0?
b0 (
0!
b0 -
b100 5
b100 =
b0 E
b101 2
b101 :
b101 B
b101 I
b101010101010101 "
b101010101010101 *
b101 1
b0 0
b1 9
b10 8
b1 A
b10 @
b101 H
b0 G
b1 ,
b10 4
b11 <
b100 D
b100 +
b11 3
b10 ;
b1 C
b100001100100001 $
b100001100100001 '
b1001000110100 #
b1001000110100 &
#80
b0 5
b0 =
b1111 2
b1111 :
b1111 B
b1111 I
b1111111111111111 "
b1111111111111111 *
b1111 1
b1111 9
b0 8
b1111 A
b0 @
b1111 H
b101 ,
b101 4
b101 <
b101 D
b1010 +
b1010 3
b1010 ;
b1010 C
b101010101010101 $
b101010101010101 '
b1010101010101010 #
b1010101010101010 &
